Workbook

Sheet 数据源粘贴在这里
A1: [日期范围]: 2024-11-28 ~ 2024-12-25
A3: 达人昵称 | B3: 达人ID | C3: 视频信息 | D3: 视频ID | E3: 发布时间 | F3: 商品 | G3: 视频vv | H3: 点赞数 | I3: 评论数 | J3: 分享数 | K3: 新增粉丝数 | L3: 引流次数 | M3: 商品曝光次数 | N3: 商品点击次数 | O3: 视频成交用户数 | P3: 视频成交订单数 | Q3: 视频成交商品件数 | R3: 视频成交金额 ($) | S3: GPM ($) | T3: 归因于可购物视频的商品交易总额 ($) | U3: 曝光点击率 | V3: 引流率 | W3: 视频完播率 | X3: 点击成交转化率 | Y3: PID | Z3: 是否开单达人 | AA3: 店铺名 | AB3: 商务还是剪辑 | AC3: 日期 | AD3: SPU
A4: aliciathecoffeequeen | B4: 6799089893735269381 | C4: I swear to you - you will LIVE in this hoodie and have ZERO regrets about buying it! #tiktokshopblackfriday #hoodie #loungewear | D4: 7437574567259950366 | E4: 45611.436 | F4: Hatant acid wash hoodie pullover oversized heavyweight cotton blend fleeced inside fabric comfy and baggy hoodies suitable for men and women faded craf vintage style hoodie | G4: 15618 | H4: 117 | I4: 5 | J4: 2 | K4: 1 | L4: 0 | M4: 16946 | N4: 1001 | O4: 12 | P4: 12 | Q4: 12 | R4: 384.44 | S4: 24.62 | T4: 384.44 | U4: 0.0641 | V4: 0 | W4: 0.0079 | X4: 0.012 | Y4: =IFERROR(VLOOKUP(F:F,#REF!,2,0),"需要手动检查") -> 需要手动检查 | Z4: =IF(R4>0,"是","否") -> 是 | AA4: 3店-Faiable Comfywear | AB4: 商务 | AC4: =YEAR(E4)&"/"&MONTH(E4)&"/"&DAY(E4) -> 2024/11/15 | AD4: =VLOOKUP(Y4,#REF!,2,FALSE) -> #REF!
A5: itttisssiii | B5: 6910792633246467077 | C5: #fyp #ootd #nooutfitrepeating #fit #schoolfit | D5: 7434966566338301227 | E5: 45604.408 | F5: Hatant Stylish Street Fashion Pullover for Women with Soft Batwing Sleeves and Big Round Neck - Breathable and Comfortable Casual Sweatshirt for All-Day Wear | G5: 136951 | H5: 19546 | I5: 53 | J5: 94 | K5: 402 | L5: 5 | M5: 196486 | N5: 20204 | O5: 6 | P5: 6 | Q5: 6 | R5: 267.94 | S5: 1.96 | T5: 267.94 | U5: 0.1475 | V5: 0.0026 | W5: 0.0952 | X5: 0.0003 | Y5: =IFERROR(VLOOKUP(F:F,#REF!,2,0),"需要手动检查") -> 需要手动检查 | Z5: =IF(R5>0,"是","否") -> 是 | AA5: 3店-Faiable Comfywear | AB5: 商务 | AC5: =YEAR(E5)&"/"&MONTH(E5)&"/"&DAY(E5) -> 2024/11/8 | AD5: =VLOOKUP(Y5,#REF!,2,FALSE) -> #REF!
A6: liliannahope | B6: 6639452985867337734 | D6: 7419426640666676511 | E6: 45562.531 | F6: Hatant Stylish Street Fashion Pullover for Women with Soft Batwing Sleeves and Big Round Neck - Breathable and Comfortable Casual Sweatshirt for All-Day Wear | G6: 18401 | H6: 623 | I6: 0 | J6: 7 | K6: 1 | L6: 0 | M6: 20318 | N6: 816 | O6: 6 | P6: 6 | Q6: 6 | R6: 257.94 | S6: 14.02 | T6: 297.03 | U6: 0.0443 | V6: 0 | W6: 0.021 | X6: 0.0074 | Y6: =IFERROR(VLOOKUP(F:F,#REF!,2,0),"需要手动检查") -> 需要手动检查 | Z6: =IF(R6>0,"是","否") -> 是 | AA6: 3店-Faiable Comfywear | AB6: 商务 | AC6: =YEAR(E6)&"/"&MONTH(E6)&"/"&DAY(E6) -> 2024/9/27 | AD6: =VLOOKUP(Y6,#REF!,2,FALSE) -> #REF!
A7: thesiuhn7oh | B7: 7301470144705725486 | C7: the cutest way to do oversized #oversized #sweatshirt #sweatshirtstyle #oversizedsweater #fashiontrend #fashiontiktok | D7: 7436732817515482410 | E7: 45609.168 | F7: Hatant Stylish Street Fashion Pullover for Women with Soft Batwing Sleeves and Big Round Neck - Breathable and Comfortable Casual Sweatshirt for All-Day Wear | G7: 3547 | H7: 29 | I7: 0 | J7: 3 | K7: 0 | L7: 0 | M7: 3764 | N7: 90 | O7: 3 | P7: 4 | Q7: 5 | R7: 233.95 | S7: 65.96 | T7: 279.94 | U7: 0.0254 | V7: 0 | W7: 0.0048 | X7: 0.0444 | Y7: =IFERROR(VLOOKUP(F:F,#REF!,2,0),"需要手动检查") -> 需要手动检查 | Z7: =IF(R7>0,"是","否") -> 是 | AA7: 3店-Faiable Comfywear | AB7: 商务 | AC7: =YEAR(E7)&"/"&MONTH(E7)&"/"&DAY(E7) -> 2024/11/13 | AD7: =VLOOKUP(Y7,#REF!,2,FALSE) -> #REF!
A8: ariyoderrr | B8: 14945948 | D8: 7413494991592443166 | E8: 45546.547 | F8: Hatant Stylish Street Fashion Pullover for Women with Soft Batwing Sleeves and Big Round Neck - Breathable and Comfortable Casual Sweatshirt for All-Day Wear | G8: 6317 | H8: 59 | I8: 0 | J8: 2 | K8: 1 | L8: 0 | M8: 6856 | N8: 158 | O8: 4 | P8: 4 | Q8: 4 | R8: 171.96 | S8: 27.22 | T8: 171.96 | U8: 0.025 | V8: 0 | W8: 0.0103 | X8: 0.0253 | Y8: =IFERROR(VLOOKUP(F:F,#REF!,2,0),"需要手动检查") -> 需要手动检查 | Z8: =IF(R8>0,"是","否") -> 是 | AA8: 3店-Faiable Comfywear | AB8: 商务 | AC8: =YEAR(E8)&"/"&MONTH(E8)&"/"&DAY(E8) -> 2024/9/11 | AD8: =VLOOKUP(Y8,#REF!,2,FALSE) -> #REF!
A9: avedaviis | B9: 6616682790505906182 | C9: byeee need more colors #offtheshouldertop #offtheshouldersweatshirt #loungewearstyle #comfystyle | D9: 7433984616203078942 | E9: 45601.762 | F9: Hatant Stylish Street Fashion Pullover for Women with Soft Batwing Sleeves and Big Round Neck - Breathable and Comfortable Casual Sweatshirt for All-Day Wear | G9: 5669 | H9: 39 | I9: 0 | J9: 0 | K9: 1 | L9: 0 | M9: 6433 | N9: 203 | O9: 3 | P9: 3 | Q9: 3 | R9: 137.06 | S9: 24.18 | T9: 229.04 | U9: 0.0358 | V9: 0 | W9: 0.0023 | X9: 0.0148 | Y9: =IFERROR(VLOOKUP(F:F,#REF!,2,0),"需要手动检查") -> 需要手动检查 | Z9: =IF(R9>0,"是","否") -> 是 | AA9: 3店-Faiable Comfywear | AB9: 商务 | AC9: =YEAR(E9)&"/"&MONTH(E9)&"/"&DAY(E9) -> 2024/11/5 | AD9: =VLOOKUP(Y9,#REF!,2,FALSE) -> #REF!
A10: dyn_alva | B10: 6806760359799735301 | C10: Acid wash hoodie sizing‼️ #acidwashhoodie #acidwash #hoodie #fall | D10: 7436108318289956138 | E10: 45607.485 | F10: Hatant acid wash hoodie pullover oversized heavyweight cotton blend fleeced inside fabric comfy and baggy hoodies suitable for men and women faded craf vintage style hoodie | G10: 3409 | H10: 26 | I10: 0 | J10: 0 | K10: 2 | L10: 0 | M10: 3821 | N10: 305 | O10: 4 | P10: 4 | Q10: 4 | R10: 136.96 | S10: 40.18 | T10: 136.96 | U10: 0.0895 | V10: 0 | W10: 0.0179 | X10: 0.0131 | Y10: =IFERROR(VLOOKUP(F:F,#REF!,2,0),"需要手动检查") -> 需要手动检查 | Z10: =IF(R10>0,"是","否") -> 是 | AA10: 3店-Faiable Comfywear | AB10: 商务 | AC10: =YEAR(E10)&"/"&MONTH(E10)&"/"&DAY(E10) -> 2024/11/11 | AD10: =VLOOKUP(Y10,#REF!,2,FALSE) -> #REF!
A11: l4mebe4n | B11: 7300300908323603499 | C11: like OBSESSED ??? | D11: 7437935508342410542 | E11: 45612.409 | F11: Hatant Stylish Street Fashion Pullover for Women with Soft Batwing Sleeves and Big Round Neck - Breathable and Comfortable Casual Sweatshirt for All-Day Wear | G11: 5250 | H11: 212 | I11: 0 | J11: 4 | K11: 0 | L11: 0 | M11: 5814 | N11: 481 | O11: 2 | P11: 3 | Q11: 3 | R11: 133.3 | S11: 25.39 | T11: 133.3 | U11: 0.0916 | V11: 0 | W11: 0.0434 | X11: 0.0062 | Y11: =IFERROR(VLOOKUP(F:F,#REF!,2,0),"需要手动检查") -> 需要手动检查 | Z11: =IF(R11>0,"是","否") -> 是 | AA11: 3店-Faiable Comfywear | AB11: 商务 | AC11: =YEAR(E11)&"/"&MONTH(E11)&"/"&DAY(E11) -> 2024/11/16 | AD11: =VLOOKUP(Y11,#REF!,2,FALSE) -> #REF!
A12: apricotolies | B12: 6532043493043355649 | C12: its just perfectly oversized #ootd #sweaterweather #hoodieszn #fall #winter #cleangirlaesthetic #ootw | D12: 7433191245385731374 | E12: 45599.624 | F12: Hatant Stylish Street Fashion Pullover for Women with Soft Batwing Sleeves and Big Round Neck - Breathable and Comfortable Casual Sweatshirt for All-Day Wear | G12: 2247 | H12: 23 | I12: 0 | J12: 0 | K12: 1 | L12: 0 | M12: 2407 | N12: 57 | O12: 3 | P12: 3 | Q12: 3 | R12: 125.06 | S12: 55.66 | T12: 125.06 | U12: 0.0254 | V12: 0 | W12: 0.0062 | X12: 0.0526 | Y12: =IFERROR(VLOOKUP(F:F,#REF!,2,0),"需要手动检查") -> 需要手动检查 | Z12: =IF(R12>0,"是","否") -> 是 | AA12: 3店-Faiable Comfywear | AB12: 商务 | AC12: =YEAR(E12)&"/"&MONTH(E12)&"/"&DAY(E12) -> 2024/11/3 | AD12: =VLOOKUP(Y12,#REF!,2,FALSE) -> #REF!
A13: hblenkhorn | B13: 6812754345839690757 | C13: the comfiest off the shoulder top. #ootd #fyp | D13: 7437638295854517550 | E13: 45611.608 | F13: Hatant Stylish Street Fashion Pullover for Women with Soft Batwing Sleeves and Big Round Neck - Breathable and Comfortable Casual Sweatshirt for All-Day Wear | G13: 9274 | H13: 259 | I13: 2 | J13: 2 | K13: 6 | L13: 0 | M13: 10222 | N13: 470 | O13: 2 | P13: 2 | Q13: 2 | R13: 95.98 | S13: 10.35 | T13: 95.98 | U13: 0.0507 | V13: 0 | W13: 0.068 | X13: 0.0043 | Y13: =IFERROR(VLOOKUP(F:F,#REF!,2,0),"需要手动检查") -> 需要手动检查 | Z13: =IF(R13>0,"是","否") -> 是 | AA13: 3店-Faiable Comfywear | AB13: 商务 | AC13: =YEAR(E13)&"/"&MONTH(E13)&"/"&DAY(E13) -> 2024/11/15 | AD13: =VLOOKUP(Y13,#REF!,2,FALSE) -> #REF!
A14: tiiffancy | B14: 6727035502945797126 | C14: The crewneck is amazing + loving the acid wash!! ❤️‍🔥❤️‍🔥 wearing a large #fyp #ootd #fitcheck #fallfashion #fall #pinterest #pinterestinspo | D14: 7435343843718974751 | E14: 45605.425 | F14: Hatant Stylish Street Fashion Pullover for Women with Soft Batwing Sleeves and Big Round Neck - Breathable and Comfortable Casual Sweatshirt for All-Day Wear | G14: 4104 | H14: 43 | I14: 0 | J14: 0 | K14: 2 | L14: 0 | M14: 5424 | N14: 158 | O14: 2 | P14: 2 | Q14: 2 | R14: 95.98 | S14: 23.39 | T14: 95.98 | U14: 0.0385 | V14: 0 | W14: 0.0068 | X14: 0.0127 | Y14: =IFERROR(VLOOKUP(F:F,#REF!,2,0),"需要手动检查") -> 需要手动检查 | Z14: =IF(R14>0,"是","否") -> 是 | AA14: 3店-Faiable Comfywear | AB14: 商务 | AC14: =YEAR(E14)&"/"&MONTH(E14)&"/"&DAY(E14) -> 2024/11/9 | AD14: =VLOOKUP(Y14,#REF!,2,FALSE) -> #REF!
A15: marteen2003 | B15: 6805300488839808006 | C15: #faiable #offtheshoulder #sweater #crewneck #hoodie | D15: 7452024455636815134 | E15: 45650.376 | F15: Hatant Stylish Street Fashion Pullover for Women with Soft Batwing Sleeves and Big Round Neck - Breathable and Comfortable Casual Sweatshirt for All-Day Wear | G15: 1013 | H15: 20 | I15: 0 | J15: 0 | K15: 0 | L15: 0 | M15: 1094 | N15: 118 | O15: 2 | P15: 2 | Q15: 2 | R15: 90.16 | S15: 89 | T15: 90.16 | U15: 0.1165 | V15: 0 | W15: 0.0128 | X15: 0.0169 | Y15: =IFERROR(VLOOKUP(F:F,#REF!,2,0),"需要手动检查") -> 需要手动检查 | Z15: =IF(R15>0,"是","否") -> 是 | AA15: 3店-Faiable Comfywear | AB15: 商务 | AC15: =YEAR(E15)&"/"&MONTH(E15)&"/"&DAY(E15) -> 2024/12/24 | AD15: =VLOOKUP(Y15,#REF!,2,FALSE) -> #REF!
A16: miahowerton | B16: 6716266466914518022 | C16: off the shoulder crewnecks are my FAV @Hatant Brand #hatant #hatanthoodie #hatantvintage #fallfashion #hoodie #crewneck #ootd #loungewear #oufitinspo | D16: 7413864423065947423 | E16: 45547.542 | F16: Hatant Stylish Street Fashion Pullover for Women with Soft Batwing Sleeves and Big Round Neck - Breathable and Comfortable Casual Sweatshirt for All-Day Wear | G16: 2722 | H16: 84 | I16: 0 | J16: 3 | K16: 0 | L16: 0 | M16: 3478 | N16: 176 | O16: 2 | P16: 2 | Q16: 2 | R16: 90.16 | S16: 33.12 | T16: 90.16 | U16: 0.0647 | V16: 0 | W16: 0.0349 | X16: 0.0114 | Y16: =IFERROR(VLOOKUP(F:F,#REF!,2,0),"需要手动检查") -> 需要手动检查 | Z16: =IF(R16>0,"是","否") -> 是 | AA16: 3店-Faiable Comfywear | AB16: 商务 | AC16: =YEAR(E16)&"/"&MONTH(E16)&"/"&DAY(E16) -> 2024/9/12 | AD16: =VLOOKUP(Y16,#REF!,2,FALSE) -> #REF!
A17: kassie_____ | B17: 5731360 | C17: Today’s gym fit. #oversizedsweaters #pumpcovers #versatilesweaters #tiktokshopblackfriday | D17: 7441369823705156907 | E17: 45621.664 | F17: Hatant Stylish Street Fashion Pullover for Women with Soft Batwing Sleeves and Big Round Neck - Breathable and Comfortable Casual Sweatshirt for All-Day Wear | G17: 1672 | H17: 77 | I17: 0 | J17: 1 | K17: 9 | L17: 0 | M17: 1793 | N17: 166 | O17: 1 | P17: 2 | Q17: 2 | R17: 87.38 | S17: 52.26 | T17: 87.38 | U17: 0.0993 | V17: 0 | W17: 0.1328 | X17: 0.012 | Y17: =IFERROR(VLOOKUP(F:F,#REF!,2,0),"需要手动检查") -> 需要手动检查 | Z17: =IF(R17>0,"是","否") -> 是 | AA17: 3店-Faiable Comfywear | AB17: 商务 | AC17: =YEAR(E17)&"/"&MONTH(E17)&"/"&DAY(E17) -> 2024/11/25 | AD17: =VLOOKUP(Y17,#REF!,2,FALSE) -> #REF!
A18: katiesantos_sahm65 | B18: 6786888663429301253 | C18: This oversize acid was hoodie is amazing. #oversizedhoodie #hoodie #acidwash #oversized #fyp | D18: 7448705237721828638 | E18: 45641.431 | F18: Hatant acid wash hoodie pullover oversized heavyweight cotton blend fleeced inside fabric comfy and baggy hoodies suitable for men and women faded craf vintage style hoodie | G18: 353 | H18: 6 | I18: 0 | J18: 0 | K18: 0 | L18: 0 | M18: 382 | N18: 8 | O18: 1 | P18: 2 | Q18: 2 | R18: 75.98 | S18: 215.24 | T18: 75.98 | U18: 0.0227 | V18: 0 | W18: 0.0028 | X18: 0.25 | Y18: =IFERROR(VLOOKUP(F:F,#REF!,2,0),"需要手动检查") -> 需要手动检查 | Z18: =IF(R18>0,"是","否") -> 是 | AA18: 3店-Faiable Comfywear | AB18: 商务 | AC18: =YEAR(E18)&"/"&MONTH(E18)&"/"&DAY(E18) -> 2024/12/15 | AD18: =VLOOKUP(Y18,#REF!,2,FALSE) -> #REF!
A19: melodylams | B19: 6684261312363545606 | D19: 7443692040837270815 | E19: 45627.922 | F19: Hatant acid wash hoodie pullover oversized heavyweight cotton blend fleeced inside fabric comfy and baggy hoodies suitable for men and women faded craf vintage style hoodie | G19: 513 | H19: 21 | I19: 1 | J19: 0 | K19: 0 | L19: 0 | M19: 509 | N19: 15 | O19: 1 | P19: 2 | Q19: 2 | R19: 75.98 | S19: 148.11 | T19: 75.98 | U19: 0.0292 | V19: 0 | W19: 0.0253 | X19: 0.1333 | Y19: =IFERROR(VLOOKUP(F:F,#REF!,2,0),"需要手动检查") -> 需要手动检查 | Z19: =IF(R19>0,"是","否") -> 是 | AA19: 3店-Faiable Comfywear | AB19: 商务 | AC19: =YEAR(E19)&"/"&MONTH(E19)&"/"&DAY(E19) -> 2024/12/1 | AD19: =VLOOKUP(Y19,#REF!,2,FALSE) -> #REF!
A20: momentswithliv | B20: 6822445842688771077 | C20: catching up on posting today ✌️😙 #ootd #comfyfits #faiablehoodie @Faiable Fashion @Faiable Comfywear #offtheshoulder #crewneck #acidwash #comfyoutfits #brandy | D20: 7429903423585127723 | E20: 45590.764 | F20: Hatant Stylish Street Fashion Pullover for Women with Soft Batwing Sleeves and Big Round Neck - Breathable and Comfortable Casual Sweatshirt for All-Day Wear | G20: 91 | H20: 0 | I20: 0 | J20: 0 | K20: 0 | L20: 0 | M20: 119 | N20: 1 | O20: 1 | P20: 2 | Q20: 2 | R20: 75.38 | S20: 828.35 | T20: 75.38 | U20: 0.011 | V20: 0 | W20: 0.033 | X20: 2 | Y20: =IFERROR(VLOOKUP(F:F,#REF!,2,0),"需要手动检查") -> 需要手动检查 | Z20: =IF(R20>0,"是","否") -> 是 | AA20: 3店-Faiable Comfywear | AB20: 商务 | AC20: =YEAR(E20)&"/"&MONTH(E20)&"/"&DAY(E20) -> 2024/10/25 | AD20: =VLOOKUP(Y20,#REF!,2,FALSE) -> #REF!
A21: lovebutts | B21: 154392151454416896 | C21: #fypage #ootd | D21: 7448341638889409835 | E21: 45640.451 | F21: Hatant acid wash hoodie pullover oversized heavyweight cotton blend fleeced inside fabric comfy and baggy hoodies suitable for men and women faded craf vintage style hoodie | G21: 4784 | H21: 160 | I21: 4 | J21: 2 | K21: 0 | L21: 0 | M21: 5205 | N21: 133 | O21: 2 | P21: 2 | Q21: 2 | R21: 63.98 | S21: 13.37 | T21: 63.98 | U21: 0.0278 | V21: 0 | W21: 0.0477 | X21: 0.015 | Y21: =IFERROR(VLOOKUP(F:F,#REF!,2,0),"需要手动检查") -> 需要手动检查 | Z21: =IF(R21>0,"是","否") -> 是 | AA21: 3店-Faiable Comfywear | AB21: 商务 | AC21: =YEAR(E21)&"/"&MONTH(E21)&"/"&DAY(E21) -> 2024/12/14 | AD21: =VLOOKUP(Y21,#REF!,2,FALSE) -> #REF!
A22: thesiuhn7oh | B22: 7301470144705725486 | C22: omg cutest oversized look possibly ever #oversized #sweatshirt #sweatshirtstyle #oversizedsweater #fashiontiktok | D22: 7438970816114593070 | E22: 45615.199 | F22: Hatant Stylish Street Fashion Pullover for Women with Soft Batwing Sleeves and Big Round Neck - Breathable and Comfortable Casual Sweatshirt for All-Day Wear | G22: 631 | H22: 5 | I22: 0 | J22: 0 | K22: 1 | L22: 0 | M22: 667 | N22: 32 | O22: 1 | P22: 1 | Q22: 1 | R22: 53.99 | S22: 85.56 | T22: 107.98 | U22: 0.0507 | V22: 0 | W22: 0.019 | X22: 0.0313 | Y22: =IFERROR(VLOOKUP(F:F,#REF!,2,0),"需要手动检查") -> 需要手动检查 | Z22: =IF(R22>0,"是","否") -> 是 | AA22: 3店-Faiable Comfywear | AB22: 商务 | AC22: =YEAR(E22)&"/"&MONTH(E22)&"/"&DAY(E22) -> 2024/11/19 | AD22: =VLOOKUP(Y22,#REF!,2,FALSE) -> #REF!
A23: malayziamarie | B23: 7271352612913021995 | C23: Size Xl , Gonna have to get in a few more colors because im kind of obsessed. 🖤 #fyp #offtheshouldersweater | D23: 7441238665432517919 | E23: 45621.31 | F23: Hatant Stylish Street Fashion Pullover for Women with Soft Batwing Sleeves and Big Round Neck - Breathable and Comfortable Casual Sweatshirt for All-Day Wear | G23: 1170 | H23: 17 | I23: 1 | J23: 1 | K23: 0 | L23: 0 | M23: 1379 | N23: 106 | O23: 1 | P23: 1 | Q23: 1 | R23: 49.99 | S23: 42.73 | T23: 49.99 | U23: 0.0906 | V23: 0 | W23: 0.194 | X23: 0.0094 | Y23: =IFERROR(VLOOKUP(F:F,#REF!,2,0),"需要手动检查") -> 需要手动检查 | Z23: =IF(R23>0,"是","否") -> 是 | AA23: 3店-Faiable Comfywear | AB23: 商务 | AC23: =YEAR(E23)&"/"&MONTH(E23)&"/"&DAY(E23) -> 2024/11/25 | AD23: =VLOOKUP(Y23,#REF!,2,FALSE) -> #REF!
A24: nphiynhi | B24: 6642365632397262853 | C24: Like a cozy blanket on me 🎧💕 #sweatshirt #offshoulder #cozyclothes #TikTokShopBlackFriday #TikTokShopHolidayHaul #TikTokShopCyberMonday #giftideas | D24: 7436505604610411822 | E24: 45608.555 | F24: Hatant Stylish Street Fashion Pullover for Women with Soft Batwing Sleeves and Big Round Neck - Breathable and Comfortable Casual Sweatshirt for All-Day Wear | G24: 418 | H24: 7 | I24: 0 | J24: 0 | K24: 0 | L24: 0 | M24: 539 | N24: 25 | O24: 1 | P24: 1 | Q24: 1 | R24: 49.99 | S24: 119.59 | T24: 49.99 | U24: 0.0598 | V24: 0 | W24: 0.0359 | X24: 0.04 | Y24: =IFERROR(VLOOKUP(F:F,#REF!,2,0),"需要手动检查") -> 需要手动检查 | Z24: =IF(R24>0,"是","否") -> 是 | AA24: 3店-Faiable Comfywear | AB24: 商务 | AC24: =YEAR(E24)&"/"&MONTH(E24)&"/"&DAY(E24) -> 2024/11/12 | AD24: =VLOOKUP(Y24,#REF!,2,FALSE) -> #REF!
A25: jules.t_ | B25: 128352 | C25: which way is your favorite? @Hatant Brand #hatant #hatanthoodie #hatantvintage 🫶🏼 | D25: 7422758501824433454 | E25: 45571.51 | F25: Hatant Stylish Street Fashion Pullover for Women with Soft Batwing Sleeves and Big Round Neck - Breathable and Comfortable Casual Sweatshirt for All-Day Wear | G25: 524 | H25: 3 | I25: 0 | J25: 1 | K25: 0 | L25: 0 | M25: 570 | N25: 12 | O25: 1 | P25: 1 | Q25: 1 | R25: 49.99 | S25: 95.4 | T25: 49.99 | U25: 0.0229 | V25: 0 | W25: 0.0592 | X25: 0.0833 | Y25: =IFERROR(VLOOKUP(F:F,#REF!,2,0),"需要手动检查") -> 需要手动检查 | Z25: =IF(R25>0,"是","否") -> 是 | AA25: 3店-Faiable Comfywear | AB25: 商务 | AC25: =YEAR(E25)&"/"&MONTH(E25)&"/"&DAY(E25) -> 2024/10/6 | AD25: =VLOOKUP(Y25,#REF!,2,FALSE) -> #REF!
A26: leaxjane | B26: 207073895185670144 | C26: This is a nice quality hoodie sweatshirt! It is fleece lined and so cozy! @Faiable Fashion @Faiable Comfywear #womensfashion #plussizefashion #midsizefashion #tiktokshopholidayhaul #winterfashion #giftideas #hoodie #oversized | D26: 7446771002828180779 | E26: 45636.219 | F26: Hatant acid wash hoodie pullover oversized heavyweight cotton blend fleeced inside fabric comfy and baggy hoodies suitable for men and women faded craf vintage style hoodie | G26: 474 | H26: 10 | I26: 0 | J26: 1 | K26: 1 | L26: 0 | M26: 566 | N26: 24 | O26: 1 | P26: 1 | Q26: 1 | R26: 45.99 | S26: 97.03 | T26: 45.99 | U26: 0.0506 | V26: 0 | W26: 0.0759 | X26: 0.0417 | Y26: =IFERROR(VLOOKUP(F:F,#REF!,2,0),"需要手动检查") -> 需要手动检查 | Z26: =IF(R26>0,"是","否") -> 是 | AA26: 3店-Faiable Comfywear | AB26: 商务 | AC26: =YEAR(E26)&"/"&MONTH(E26)&"/"&DAY(E26) -> 2024/12/10 | AD26: =VLOOKUP(Y26,#REF!,2,FALSE) -> #REF!
A27: everyday_tina | B27: 6804619634186077190 | C27: So cozy and comfy!! #outfitsinspo #tiktokshop #fyp | D27: 7440105853669149998 | E27: 45618.257 | F27: Hatant Stylish Street Fashion Pullover for Women with Soft Batwing Sleeves and Big Round Neck - Breathable and Comfortable Casual Sweatshirt for All-Day Wear | G27: 412 | H27: 2 | I27: 0 | J27: 0 | K27: 0 | L27: 0 | M27: 436 | N27: 26 | O27: 1 | P27: 1 | Q27: 1 | R27: 45.99 | S27: 111.63 | T27: 45.99 | U27: 0.0631 | V27: 0 | W27: 0.0024 | X27: 0.0385 | Y27: =IFERROR(VLOOKUP(F:F,#REF!,2,0),"需要手动检查") -> 需要手动检查 | Z27: =IF(R27>0,"是","否") -> 是 | AA27: 3店-Faiable Comfywear | AB27: 商务 | AC27: =YEAR(E27)&"/"&MONTH(E27)&"/"&DAY(E27) -> 2024/11/22 | AD27: =VLOOKUP(Y27,#REF!,2,FALSE) -> #REF!
A28: iamkay2024 | B28: 7288982162065441838 | C28: i mean RUN. 🏃‍♀️💙❄️ #sweater #sweaterweather #offtheshouldersweater #fall #winter #tiktokshopblackfriday | D28: 7438812703596072223 | E28: 45614.773 | F28: Hatant Stylish Street Fashion Pullover for Women with Soft Batwing Sleeves and Big Round Neck - Breathable and Comfortable Casual Sweatshirt for All-Day Wear | G28: 211 | H28: 3 | I28: 0 | J28: 0 | K28: 0 | L28: 0 | M28: 240 | N28: 5 | O28: 1 | P28: 1 | Q28: 1 | R28: 45.99 | S28: 217.96 | T28: 91.07 | U28: 0.0237 | V28: 0 | W28: 0.0284 | X28: 0.2 | Y28: =IFERROR(VLOOKUP(F:F,#REF!,2,0),"需要手动检查") -> 需要手动检查 | Z28: =IF(R28>0,"是","否") -> 是 | AA28: 3店-Faiable Comfywear | AB28: 商务 | AC28: =YEAR(E28)&"/"&MONTH(E28)&"/"&DAY(E28) -> 2024/11/18 | AD28: =VLOOKUP(Y28,#REF!,2,FALSE) -> #REF!
A29: chamley_teaches | B29: 6783887103179113477 | C29: if you loved the acid wash hoodie, you will love the crewneck 🫶🏽 wearing size medium !! #tiktokshop #tiktokshopfinds #acidwash #hoodie #hoodies #hoodieszn #acidwashhoodie #crewneck #crewnecksweatshirt #oversizedhoodie | D29: 7431556464403057951 | E29: 45595.219 | F29: Hatant Stylish Street Fashion Pullover for Women with Soft Batwing Sleeves and Big Round Neck - Breathable and Comfortable Casual Sweatshirt for All-Day Wear | G29: 5487 | H29: 33 | I29: 0 | J29: 1 | K29: 0 | L29: 0 | M29: 6056 | N29: 97 | O29: 1 | P29: 1 | Q29: 1 | R29: 45.99 | S29: 8.38 | T29: 91.07 | U29: 0.0177 | V29: 0 | W29: 0.027 | X29: 0.0103 | Y29: =IFERROR(VLOOKUP(F:F,#REF!,2,0),"需要手动检查") -> 需要手动检查 | Z29: =IF(R29>0,"是","否") -> 是 | AA29: 3店-Faiable Comfywear | AB29: 商务 | AC29: =YEAR(E29)&"/"&MONTH(E29)&"/"&DAY(E29) -> 2024/10/30 | AD29: =VLOOKUP(Y29,#REF!,2,FALSE) -> #REF!
A30: ariyoderrr | B30: 14945948 | C30: Linked above^^^ im 5’4 and got a size medium #fyp #crewneck #sweaterweather #cutesweatshirts #cutefalloutfits #collegeoutfit #comfy #pink #offtheshoulder #trending #viral | D30: 7412392895409343775 | E30: 45543.577 | F30: Hatant Stylish Street Fashion Pullover for Women with Soft Batwing Sleeves and Big Round Neck - Breathable and Comfortable Casual Sweatshirt for All-Day Wear | G30: 844 | H30: 2 | I30: 0 | J30: 0 | K30: 0 | L30: 0 | M30: 984 | N30: 27 | O30: 1 | P30: 1 | Q30: 1 | R30: 45.99 | S30: 54.49 | T30: 45.99 | U30: 0.032 | V30: 0 | W30: 0.0569 | X30: 0.037 | Y30: =IFERROR(VLOOKUP(F:F,#REF!,2,0),"需要手动检查") -> 需要手动检查 | Z30: =IF(R30>0,"是","否") -> 是 | AA30: 3店-Faiable Comfywear | AB30: 商务 | AC30: =YEAR(E30)&"/"&MONTH(E30)&"/"&DAY(E30) -> 2024/9/8 | AD30: =VLOOKUP(Y30,#REF!,2,FALSE) -> #REF!
A31: avedaviis | B31: 6616682790505906182 | C31: sweatshirts all day 🫶🏼 | D31: 7434733452278156575 | E31: 45603.78 | F31: Hatant Stylish Street Fashion Pullover for Women with Soft Batwing Sleeves and Big Round Neck - Breathable and Comfortable Casual Sweatshirt for All-Day Wear | G31: 592 | H31: 6 | I31: 2 | J31: 0 | K31: 0 | L31: 0 | M31: 640 | N31: 13 | O31: 1 | P31: 1 | Q31: 1 | R31: 45.08 | S31: 76.15 | T31: 45.08 | U31: 0.022 | V31: 0 | W31: 0.027 | X31: 0.0769 | Y31: =IFERROR(VLOOKUP(F:F,#REF!,2,0),"需要手动检查") -> 需要手动检查 | Z31: =IF(R31>0,"是","否") -> 是 | AA31: 3店-Faiable Comfywear | AB31: 商务 | AC31: =YEAR(E31)&"/"&MONTH(E31)&"/"&DAY(E31) -> 2024/11/7 | AD31: =VLOOKUP(Y31,#REF!,2,FALSE) -> #REF!
... A44: keriannkuzmin | B44: 6768690888581760005 | C44: Something about an oversized hoodie🎀 #hoodie #jacket #fashion #hoodieszn | D44: 7446893980408679722 | E44: 45636.55 | F44: Hatant acid wash hoodie pullover oversized heavyweight cotton blend fleeced inside fabric comfy and baggy hoodies suitable for men and women faded craf vintage style hoodie | G44: 907 | H44: 60 | I44: 2 | J44: 3 | K44: 0 | L44: 0 | M44: 1030 | N44: 8 | O44: 1 | P44: 1 | Q44: 1 | R44: 25.99 | S44: 28.65 | T44: 25.99 | U44: 0.0088 | V44: 0 | W44: 0.0485 | X44: 0.125 | Y44: =IFERROR(VLOOKUP(F:F,#REF!,2,0),"需要手动检查") -> 需要手动检查 | Z44: =IF(R44>0,"是","否") -> 是 | AA44: 3店-Faiable Comfywear | AB44: 商务 | AC44: =YEAR(E44)&"/"&MONTH(E44)&"/"&DAY(E44) -> 2024/12/10 | AD44: =VLOOKUP(Y44,#REF!,2,FALSE) -> #REF!
A45: emilyannmcgill | B45: 7117440140370789422 | D45: 7403933968673885471 | E45: 45520.782 | F45: Hatant Sweatshirt for Women Acid Wash Athletic Hoodie Heritage Fleece V-neck Long Sleeve Hoodie Fleece Women Sweatshirt,nice fell soft fabric,perfect crop length,suitable for running errands, relaxing at home,flattering style washed hoodie | G45: 37 | H45: 7 | I45: 0 | J45: 0 | K45: 0 | L45: 0 | M45: 44 | N45: 10 | O45: 1 | P45: 1 | Q45: 1 | R45: 13.03 | S45: 352.16 | T45: 13.03 | U45: 0.2703 | V45: 0 | W45: 0 | X45: 0.1 | Y45: =IFERROR(VLOOKUP(F:F,#REF!,2,0),"需要手动检查") -> 需要手动检查 | Z45: =IF(R45>0,"是","否") -> 是 | AA45: 3店-Faiable Comfywear | AB45: 商务 | AC45: =YEAR(E45)&"/"&MONTH(E45)&"/"&DAY(E45) -> 2024/8/16 | AD45: =VLOOKUP(Y45,#REF!,2,FALSE) -> #REF!
A46: aleksamink | B46: 25195448 | C46: Thick and affordable #tiktokshop #fashionfinds #thick #curves #bodypositivity | D46: 7452570087699074346 | E46: 45651.846 | F46: Hatant acid wash hoodie pullover oversized heavyweight cotton blend fleeced inside fabric comfy and baggy hoodies suitable for men and women faded craf vintage style hoodie | G46: 2067 | H46: 104 | I46: 6 | J46: 0 | K46: 2 | L46: 0 | M46: 1876 | N46: 23 | O46: 0 | P46: 0 | Q46: 0 | R46: 0 | S46: 0 | T46: 0 | U46: 0.0111 | V46: 0 | W46: 0.0479 | X46: 0 | Y46: =IFERROR(VLOOKUP(F:F,#REF!,2,0),"需要手动检查") -> 需要手动检查 | Z46: =IF(R46>0,"是","否") -> 否 | AA46: 3店-Faiable Comfywear | AB46: 商务 | AC46: =YEAR(E46)&"/"&MONTH(E46)&"/"&DAY(E46) -> 2024/12/25 | AD46: =VLOOKUP(Y46,#REF!,2,FALSE) -> #REF!
A47: natalia199326 | B47: 6745777028622435333 | C47: Hatant acid wash hoodie pullov Sudadera de muy buena calidad perfecta para temporada de frío 🫶 #hatant #wash #sudaderas #sudadera #sudaderaoversize #comoda #Navidad #Christmas | D47: 7452369711326678315 | E47: 45651.306 | F47: Hatant acid wash hoodie pullover oversized heavyweight cotton blend fleeced inside fabric comfy and baggy hoodies suitable for men and women faded craf vintage style hoodie | G47: 448 | H47: 23 | I47: 6 | J47: 10 | K47: 1 | L47: 0 | M47: 456 | N47: 19 | O47: 0 | P47: 0 | Q47: 0 | R47: 0 | S47: 0 | T47: 0 | U47: 0.0424 | V47: 0 | W47: 0.0603 | X47: 0 | Y47: =IFERROR(VLOOKUP(F:F,#REF!,2,0),"需要手动检查") -> 需要手动检查 | Z47: =IF(R47>0,"是","否") -> 否 | AA47: 3店-Faiable Comfywear | AB47: 商务 | AC47: =YEAR(E47)&"/"&MONTH(E47)&"/"&DAY(E47) -> 2024/12/25 | AD47: =VLOOKUP(Y47,#REF!,2,FALSE) -> #REF!
A48: therealtina_4444 | B48: 6924048352968606726 | C48: Size small true size, many different colors and styles to choose from #musthaves #tiktokshop #sweater #fashion #smallbusiness #fyp #womensfashion | D48: 7452365023457987871 | E48: 45651.294 | F48: Hatant Stylish Street Fashion Pullover for Women with Soft Batwing Sleeves and Big Round Neck - Breathable and Comfortable Casual Sweatshirt for All-Day Wear | G48: 374 | H48: 34 | I48: 6 | J48: 0 | K48: 1 | L48: 0 | M48: 419 | N48: 46 | O48: 0 | P48: 0 | Q48: 0 | R48: 0 | S48: 0 | T48: 0 | U48: 0.123 | V48: 0 | W48: 0.0561 | X48: 0 | Y48: =IFERROR(VLOOKUP(F:F,#REF!,2,0),"需要手动检查") -> 需要手动检查 | Z48: =IF(R48>0,"是","否") -> 否 | AA48: 3店-Faiable Comfywear | AB48: 商务 | AC48: =YEAR(E48)&"/"&MONTH(E48)&"/"&DAY(E48) -> 2024/12/25 | AD48: =VLOOKUP(Y48,#REF!,2,FALSE) -> #REF!
A49: harabaraaa | B49: 4312452 | C49: #gossipgirl #oversizedshirt #cozy #tiktokshopfinds | D49: 7452273728341216555 | E49: 45651.047 | F49: Hatant Stylish Street Fashion Pullover for Women with Soft Batwing Sleeves and Big Round Neck - Breathable and Comfortable Casual Sweatshirt for All-Day Wear | G49: 296 | H49: 5 | I49: 0 | J49: 0 | K49: 0 | L49: 0 | M49: 324 | N49: 3 | O49: 0 | P49: 0 | Q49: 0 | R49: 0 | S49: 0 | T49: 0 | U49: 0.0101 | V49: 0 | W49: 0.0405 | X49: 0 | Y49: =IFERROR(VLOOKUP(F:F,#REF!,2,0),"需要手动检查") -> 需要手动检查 | Z49: =IF(R49>0,"是","否") -> 否 | AA49: 3店-Faiable Comfywear | AB49: 商务 | AC49: =YEAR(E49)&"/"&MONTH(E49)&"/"&DAY(E49) -> 2024/12/25 | AD49: =VLOOKUP(Y49,#REF!,2,FALSE) -> #REF!
A50: harabaraaa | B50: 4312452 | C50: #cozy #oversized #tiktokshop #tiktokshopfinds | D50: 7452272707929902382 | E50: 45651.045 | F50: Hatant Stylish Street Fashion Pullover for Women with Soft Batwing Sleeves and Big Round Neck - Breathable and Comfortable Casual Sweatshirt for All-Day Wear | G50: 295 | H50: 6 | I50: 0 | J50: 0 | K50: 0 | L50: 0 | M50: 287 | N50: 6 | O50: 0 | P50: 0 | Q50: 0 | R50: 0 | S50: 0 | T50: 0 | U50: 0.0203 | V50: 0 | W50: 0.0203 | X50: 0 | Y50: =IFERROR(VLOOKUP(F:F,#REF!,2,0),"需要手动检查") -> 需要手动检查 | Z50: =IF(R50>0,"是","否") -> 否 | AA50: 3店-Faiable Comfywear | AB50: 商务 | AC50: =YEAR(E50)&"/"&MONTH(E50)&"/"&DAY(E50) -> 2024/12/25 | AD50: =VLOOKUP(Y50,#REF!,2,FALSE) -> #REF!
A51: kairienos | B51: 6952974567241565189 | C51: MERRY CHRISTMAS EVE ❤️💋🎁 @Faiable Fashion #faiable #faiablehoodie #faiablefashion #hoodie #hoodieszn #hoodieseason #hoodiesthathoodie #redhoodie #christmaseve #christmas | D51: 7452206129846865198 | E51: 45650.865 | F51: Hatant acid wash hoodie pullover oversized heavyweight cotton blend fleeced inside fabric comfy and baggy hoodies suitable for men and women faded craf vintage style hoodie | G51: 591 | H51: 55 | I51: 15 | J51: 2 | K51: 0 | L51: 0 | M51: 637 | N51: 51 | O51: 0 | P51: 0 | Q51: 0 | R51: 0 | S51: 0 | T51: 0 | U51: 0.0863 | V51: 0 | W51: 0.0288 | X51: 0 | Y51: =IFERROR(VLOOKUP(F:F,#REF!,2,0),"需要手动检查") -> 需要手动检查 | Z51: =IF(R51>0,"是","否") -> 否 | AA51: 3店-Faiable Comfywear | AB51: 商务 | AC51: =YEAR(E51)&"/"&MONTH(E51)&"/"&DAY(E51) -> 2024/12/24 | AD51: =VLOOKUP(Y51,#REF!,2,FALSE) -> #REF!
A52: jennmalentacchi | B52: 6765262976972981253 | C52: I have loved these sweatpants since the day I got them. You can’t even tell how many times I have washed them.@Faiable Comfywear #Sweatpants #HatAant #Joggers #Pockets #Pajamas #Athletic #Loungewear #Leisurewear #ColdWeather #SweaterWeather #TikTokShop #TikTokFashion | D52: 7452102310211177758 | E52: 45650.586 | F52: Hatant heavyweight fleeced comfy and soft baggy sweatpants cotton 345gsm fabric S-2XL true size bottoms Elastic waistband drawstring | G52: 298 | H52: 9 | I52: 1 | J52: 0 | K52: 0 | L52: 0 | M52: 315 | N52: 3 | O52: 0 | P52: 0 | Q52: 0 | R52: 0 | S52: 0 | T52: 0 | U52: 0.0101 | V52: 0 | W52: 0.0201 | X52: 0 | Y52: =IFERROR(VLOOKUP(F:F,#REF!,2,0),"需要手动检查") -> 需要手动检查 | Z52: =IF(R52>0,"是","否") -> 否 | AA52: 3店-Faiable Comfywear | AB52: 商务 | AC52: =YEAR(E52)&"/"&MONTH(E52)&"/"&DAY(E52) -> 2024/12/24 | AD52: =VLOOKUP(Y52,#REF!,2,FALSE) -> #REF!
A53: momma_mya | B53: 6908047646339531781 | C53: Its so nice i love it. Gonna be worn to the gym for the next 6 months lmaooo #gymclothes #pumpcover #hoodieweather #hoodie #sweatshirtsesaon #gymtok #gymfit #pumpcovers #bodybuilding #bodybuilders #gymgirls #cozyseason | D53: 7452096927048469806 | E53: 45650.571 | F53: Hatant acid wash hoodie pullover oversized heavyweight cotton blend fleeced inside fabric comfy and baggy hoodies suitable for men and women faded craf vintage style hoodie | G53: 386 | H53: 22 | I53: 0 | J53: 2 | K53: 0 | L53: 0 | M53: 426 | N53: 14 | O53: 0 | P53: 0 | Q53: 0 | R53: 0 | S53: 0 | T53: 0 | U53: 0.0363 | V53: 0 | W53: 0.1399 | X53: 0 | Y53: =IFERROR(VLOOKUP(F:F,#REF!,2,0),"需要手动检查") -> 需要手动检查 | Z53: =IF(R53>0,"是","否") -> 否 | AA53: 3店-Faiable Comfywear | AB53: 商务 | AC53: =YEAR(E53)&"/"&MONTH(E53)&"/"&DAY(E53) -> 2024/12/24 | AD53: =VLOOKUP(Y53,#REF!,2,FALSE) -> #REF!
A54: everyday_tina | B54: 6804619634186077190 | C54: Comfy outfit! #outfitinspo #fyp #tiktokshop #OOTD #comfy | D54: 7452021711681244447 | E54: 45650.368 | F54: Hatant Stylish Street Fashion Pullover for Women with Soft Batwing Sleeves and Big Round Neck - Breathable and Comfortable Casual Sweatshirt for All-Day Wear | G54: 350 | H54: 56 | I54: 3 | J54: 1 | K54: 0 | L54: 0 | M54: 385 | N54: 16 | O54: 0 | P54: 0 | Q54: 0 | R54: 0 | S54: 0 | T54: 0 | U54: 0.0457 | V54: 0 | W54: 0.02 | X54: 0 | Y54: =IFERROR(VLOOKUP(F:F,#REF!,2,0),"需要手动检查") -> 需要手动检查 | Z54: =IF(R54>0,"是","否") -> 否 | AA54: 3店-Faiable Comfywear | AB54: 商务 | AC54: =YEAR(E54)&"/"&MONTH(E54)&"/"&DAY(E54) -> 2024/12/24 | AD54: =VLOOKUP(Y54,#REF!,2,FALSE) -> #REF!
A55: toriyaki..chicken | B55: 7276820263466222638 | C55: I LOVEEEEE #oversized #oversizedhoodie #acidwashhoodie #pink #pinkaesthetic #pinkgirl #pinkgirly #christmaseve #tiktokshopfinds | D55: 7451995902295723310 | E55: 45650.299 | F55: Hatant acid wash hoodie pullover oversized heavyweight cotton blend fleeced inside fabric comfy and baggy hoodies suitable for men and women faded craf vintage style hoodie | G55: 350 | H55: 24 | I55: 3 | J55: 0 | K55: 0 | L55: 0 | M55: 409 | N55: 20 | O55: 0 | P55: 0 | Q55: 0 | R55: 0 | S55: 0 | T55: 0 | U55: 0.0571 | V55: 0 | W55: 0.0229 | X55: 0 | Y55: =IFERROR(VLOOKUP(F:F,#REF!,2,0),"需要手动检查") -> 需要手动检查 | Z55: =IF(R55>0,"是","否") -> 否 | AA55: 3店-Faiable Comfywear | AB55: 商务 | AC55: =YEAR(E55)&"/"&MONTH(E55)&"/"&DAY(E55) -> 2024/12/24 | AD55: =VLOOKUP(Y55,#REF!,2,FALSE) -> #REF!
A56: chamley_teaches | B56: 6783887103179113477 | C56: like this if you think my fiancé should buy me a puppy 🥺 oh and this sweatshirt is perfectttt (size m) #tiktokshopfinds #tiktokshopholidayhaul #sweaterweather #sweater #crewneck #crewnecksweatshirt #acidwashhoodie #sweatshirt | D56: 7451974816657100062 | E56: 45650.242 | F56: Hatant Stylish Street Fashion Pullover for Women with Soft Batwing Sleeves and Big Round Neck - Breathable and Comfortable Casual Sweatshirt for All-Day Wear | G56: 404 | H56: 42 | I56: 16 | J56: 3 | K56: 0 | L56: 0 | M56: 451 | N56: 30 | O56: 0 | P56: 0 | Q56: 0 | R56: 0 | S56: 0 | T56: 0 | U56: 0.0743 | V56: 0 | W56: 0.0743 | X56: 0 | Y56: =IFERROR(VLOOKUP(F:F,#REF!,2,0),"需要手动检查") -> 需要手动检查 | Z56: =IF(R56>0,"是","否") -> 否 | AA56: 3店-Faiable Comfywear | AB56: 商务 | AC56: =YEAR(E56)&"/"&MONTH(E56)&"/"&DAY(E56) -> 2024/12/24 | AD56: =VLOOKUP(Y56,#REF!,2,FALSE) -> #REF!
A57: moebunnyy | B57: 6653842064910942213 | D57: 7451923955880906015 | E57: 45650.105 | F57: Hatant acid wash hoodie pullover oversized heavyweight cotton blend fleeced inside fabric comfy and baggy hoodies suitable for men and women faded craf vintage style hoodie | G57: 8 | H57: 0 | I57: 0 | J57: 0 | K57: 0 | L57: 0 | M57: 8 | N57: 0 | O57: 0 | P57: 0 | Q57: 0 | R57: 0 | S57: 0 | T57: 0 | U57: 0 | V57: 0 | W57: 0 | X57: 0 | Y57: =IFERROR(VLOOKUP(F:F,#REF!,2,0),"需要手动检查") -> 需要手动检查 | Z57: =IF(R57>0,"是","否") -> 否 | AA57: 3店-Faiable Comfywear | AB57: 商务 | AC57: =YEAR(E57)&"/"&MONTH(E57)&"/"&DAY(E57) -> 2024/12/24 | AD57: =VLOOKUP(Y57,#REF!,2,FALSE) -> #REF!
A58: alexiswells | B58: 7130795479730439210 | C58: My mini built in bestie. I love you so much son. Forever and always. #greenscreenvideo #mama #son #iloveu #fyp #foryoupage #foryou #love | D58: 7451892504099589407 | E58: 45650.02 | F58: Hatant acid wash hoodie pullover oversized heavyweight cotton blend fleeced inside fabric comfy and baggy hoodies suitable for men and women faded craf vintage style hoodie | G58: 330 | H58: 41 | I58: 0 | J58: 0 | K58: 0 | L58: 0 | M58: 340 | N58: 0 | O58: 0 | P58: 0 | Q58: 0 | R58: 0 | S58: 0 | T58: 0 | U58: 0 | V58: 0 | W58: 0.0727 | X58: 0 | Y58: =IFERROR(VLOOKUP(F:F,#REF!,2,0),"需要手动检查") -> 需要手动检查 | Z58: =IF(R58>0,"是","否") -> 否 | AA58: 3店-Faiable Comfywear | AB58: 商务 | AC58: =YEAR(E58)&"/"&MONTH(E58)&"/"&DAY(E58) -> 2024/12/24 | AD58: =VLOOKUP(Y58,#REF!,2,FALSE) -> #REF!
A59: jessagoldd | B59: 6629132633325240326 | D59: 7451872539170589982 | E59: 45649.966 | F59: Hatant Stylish Street Fashion Pullover for Women with Soft Batwing Sleeves and Big Round Neck - Breathable and Comfortable Casual Sweatshirt for All-Day Wear | G59: 396 | H59: 19 | I59: 0 | J59: 0 | K59: 1 | L59: 0 | M59: 410 | N59: 1 | O59: 0 | P59: 0 | Q59: 0 | R59: 0 | S59: 0 | T59: 0 | U59: 0.0025 | V59: 0 | W59: 0.0152 | X59: 0 | Y59: =IFERROR(VLOOKUP(F:F,#REF!,2,0),"需要手动检查") -> 需要手动检查 | Z59: =IF(R59>0,"是","否") -> 否 | AA59: 3店-Faiable Comfywear | AB59: 商务 | AC59: =YEAR(E59)&"/"&MONTH(E59)&"/"&DAY(E59) -> 2024/12/23 | AD59: =VLOOKUP(Y59,#REF!,2,FALSE) -> #REF!
A60: thecrookschaos | B60: 6778145611206198278 | C60: #creatorsearchinsights #casualfootball #casualfootballstyle #gameday #womensfashion #womenswear #freeshipping #jersey #sportswear #womenswear #tiktokshoplastchance #tiktokshopnewyearnewaura | D60: 7451850358554397995 | E60: 45649.906 | F60: Hatant Stylish Street Fashion Pullover for Women with Soft Batwing Sleeves and Big Round Neck - Breathable and Comfortable Casual Sweatshirt for All-Day Wear | G60: 340 | H60: 16 | I60: 2 | J60: 1 | K60: 0 | L60: 0 | M60: 383 | N60: 10 | O60: 0 | P60: 0 | Q60: 0 | R60: 0 | S60: 0 | T60: 0 | U60: 0.0294 | V60: 0 | W60: 0.0412 | X60: 0 | Y60: =IFERROR(VLOOKUP(F:F,#REF!,2,0),"需要手动检查") -> 需要手动检查 | Z60: =IF(R60>0,"是","否") -> 否 | AA60: 3店-Faiable Comfywear | AB60: 商务 | AC60: =YEAR(E60)&"/"&MONTH(E60)&"/"&DAY(E60) -> 2024/12/23 | AD60: =VLOOKUP(Y60,#REF!,2,FALSE) -> #REF!
A61: lirazzb | B61: 6746154716546597894 | C61: 🥰 #tiktokshop | D61: 7451813337815403818 | E61: 45649.807 | F61: Hatant Stylish Street Fashion Pullover for Women with Soft Batwing Sleeves and Big Round Neck - Breathable and Comfortable Casual Sweatshirt for All-Day Wear | G61: 894 | H61: 14 | I61: 0 | J61: 1 | K61: 0 | L61: 0 | M61: 847 | N61: 3 | O61: 0 | P61: 0 | Q61: 0 | R61: 0 | S61: 0 | T61: 0 | U61: 0.0034 | V61: 0 | W61: 0.0302 | X61: 0 | Y61: =IFERROR(VLOOKUP(F:F,#REF!,2,0),"需要手动检查") -> 需要手动检查 | Z61: =IF(R61>0,"是","否") -> 否 | AA61: 3店-Faiable Comfywear | AB61: 商务 | AC61: =YEAR(E61)&"/"&MONTH(E61)&"/"&DAY(E61) -> 2024/12/23 | AD61: =VLOOKUP(Y61,#REF!,2,FALSE) -> #REF!
A62: lirazzb | B62: 6746154716546597894 | C62: 🥰 #tiktokshop | D62: 7451813042200907051 | E62: 45649.806 | F62: Hatant Stylish Street Fashion Pullover for Women with Soft Batwing Sleeves and Big Round Neck - Breathable and Comfortable Casual Sweatshirt for All-Day Wear | G62: 1 | H62: 0 | I62: 0 | J62: 1 | K62: 0 | L62: 0 | M62: 0 | N62: 0 | O62: 0 | P62: 0 | Q62: 0 | R62: 0 | S62: 0 | T62: 0 | U62: 0 | V62: 0 | W62: 0 | X62: 0 | Y62: =IFERROR(VLOOKUP(F:F,#REF!,2,0),"需要手动检查") -> 需要手动检查 | Z62: =IF(R62>0,"是","否") -> 否 | AA62: 3店-Faiable Comfywear | AB62: 商务 | AC62: =YEAR(E62)&"/"&MONTH(E62)&"/"&DAY(E62) -> 2024/12/23 | AD62: =VLOOKUP(Y62,#REF!,2,FALSE) -> #REF!
A63: kerryc1208 | B63: 7355684352792052782 | C63: this oversized hoodie is the comfiest & most flattering! #tiktokshop #oversizedhoodie #comfy #comfyhoodie #creatorsearchinsights Comfy and affordable hoodie Oversized hoodie Best oversized hoodie | D63: 7451812262404263214 | E63: 45649.804 | F63: Hatant acid wash hoodie pullover oversized heavyweight cotton blend fleeced inside fabric comfy and baggy hoodies suitable for men and women faded craf vintage style hoodie | G63: 300 | H63: 15 | I63: 4 | J63: 1 | K63: 0 | L63: 0 | M63: 311 | N63: 28 | O63: 0 | P63: 0 | Q63: 0 | R63: 0 | S63: 0 | T63: 0 | U63: 0.0933 | V63: 0 | W63: 0.02 | X63: 0 | Y63: =IFERROR(VLOOKUP(F:F,#REF!,2,0),"需要手动检查") -> 需要手动检查 | Z63: =IF(R63>0,"是","否") -> 否 | AA63: 3店-Faiable Comfywear | AB63: 商务 | AC63: =YEAR(E63)&"/"&MONTH(E63)&"/"&DAY(E63) -> 2024/12/23 | AD63: =VLOOKUP(Y63,#REF!,2,FALSE) -> #REF!
A64: average.mom.next.door | B64: 6897944124558885893 | C64: Teacher OOTD Holiday Edition with my favorite Wide Leg Velvet Pants @Faiable Comfywear #faiablecomfywear #ootdinspo #teacherootd #holidayfashion #holidayootd #velvet #velvetpants #holidayoutfit #widelegpants #holidaybreak #christmasoutfit | D64: 7451803124639075626 | E64: 45649.779 | F64: Faiable Velvet Pants for Women High Waisted Wide Leg Palazzo Pants Causal Outfits Long Flowy Trousers with Pockets flattering pants Womenswear Bottom | G64: 299 | H64: 24 | I64: 14 | J64: 1 | K64: 0 | L64: 0 | M64: 275 | N64: 5 | O64: 0 | P64: 0 | Q64: 0 | R64: 0 | S64: 0 | T64: 0 | U64: 0.0167 | V64: 0 | W64: 0.0201 | X64: 0 | Y64: =IFERROR(VLOOKUP(F:F,#REF!,2,0),"需要手动检查") -> 需要手动检查 | Z64: =IF(R64>0,"是","否") -> 否 | AA64: 3店-Faiable Comfywear | AB64: 商务 | AC64: =YEAR(E64)&"/"&MONTH(E64)&"/"&DAY(E64) -> 2024/12/23 | AD64: =VLOOKUP(Y64,#REF!,2,FALSE) -> #REF!
A65: yourdealsbestie | B65: 7328451096199087146 | C65: Trying on the cropped sweatshirt by faiable #sweatshirt #faiable #fleece #croppedsweater #vneck #y2k #academiccore #vintagestyle #sweaterweather #tiktokfashion | D65: 7451765341081865514 | E65: 45649.677 | F65: Hatant Sweatshirt for Women Acid Wash Athletic Hoodie Heritage Fleece V-neck Long Sleeve Hoodie Fleece Women Sweatshirt,nice fell soft fabric,perfect crop length,suitable for running errands, relaxing at home,flattering style washed hoodie | G65: 310 | H65: 4 | I65: 0 | J65: 0 | K65: 0 | L65: 0 | M65: 336 | N65: 23 | O65: 0 | P65: 0 | Q65: 0 | R65: 0 | S65: 0 | T65: 0 | U65: 0.0742 | V65: 0 | W65: 0 | X65: 0 | Y65: =IFERROR(VLOOKUP(F:F,#REF!,2,0),"需要手动检查") -> 需要手动检查 | Z65: =IF(R65>0,"是","否") -> 否 | AA65: 3店-Faiable Comfywear | AB65: 商务 | AC65: =YEAR(E65)&"/"&MONTH(E65)&"/"&DAY(E65) -> 2024/12/23 | AD65: =VLOOKUP(Y65,#REF!,2,FALSE) -> #REF!
A66: buffalochickendipbby | B66: 6720051716371645445 | C66: This brand doesn’t miss | D66: 7451751885804932383 | E66: 45649.641 | F66: Hatant Stylish Street Fashion Pullover for Women with Soft Batwing Sleeves and Big Round Neck - Breathable and Comfortable Casual Sweatshirt for All-Day Wear | G66: 638 | H66: 36 | I66: 1 | J66: 1 | K66: 0 | L66: 0 | M66: 566 | N66: 25 | O66: 0 | P66: 0 | Q66: 0 | R66: 0 | S66: 0 | T66: 0 | U66: 0.0392 | V66: 0 | W66: 0.0329 | X66: 0 | Y66: =IFERROR(VLOOKUP(F:F,#REF!,2,0),"需要手动检查") -> 需要手动检查 | Z66: =IF(R66>0,"是","否") -> 否 | AA66: 3店-Faiable Comfywear | AB66: 商务 | AC66: =YEAR(E66)&"/"&MONTH(E66)&"/"&DAY(E66) -> 2024/12/23 | AD66: =VLOOKUP(Y66,#REF!,2,FALSE) -> #REF!
A67: lyfewithabi | B67: 7364204940607816747 | C67: #fyp | D67: 7451745619003297070 | E67: 45649.624 | F67: Hatant Stylish Street Fashion Pullover for Women with Soft Batwing Sleeves and Big Round Neck - Breathable and Comfortable Casual Sweatshirt for All-Day Wear | G67: 833 | H67: 58 | I67: 4 | J67: 0 | K67: 1 | L67: 0 | M67: 814 | N67: 56 | O67: 0 | P67: 0 | Q67: 0 | R67: 0 | S67: 0 | T67: 0 | U67: 0.0672 | V67: 0 | W67: 0.1104 | X67: 0 | Y67: =IFERROR(VLOOKUP(F:F,#REF!,2,0),"需要手动检查") -> 需要手动检查 | Z67: =IF(R67>0,"是","否") -> 否 | AA67: 3店-Faiable Comfywear | AB67: 商务 | AC67: =YEAR(E67)&"/"&MONTH(E67)&"/"&DAY(E67) -> 2024/12/23 | AD67: =VLOOKUP(Y67,#REF!,2,FALSE) -> #REF!
A68: jennmalentacchi2 | B68: 7319968933406688302 | C68: I love these sweatpants. They are not super expensive either. I could live in these. @Faiable Fashion #hatant #Sweatpants #Pajamas #ComfyClothes #TikTokShopFind #Unisex #UnisexSweatpants #Joggers | D68: 7451735590879579438 | E68: 45649.597 | F68: Hatant heavyweight fleeced comfy and soft baggy sweatpants cotton 345gsm fabric S-2XL true size bottoms Elastic waistband drawstring | G68: 304 | H68: 16 | I68: 6 | J68: 1 | K68: 2 | L68: 0 | M68: 316 | N68: 4 | O68: 0 | P68: 0 | Q68: 0 | R68: 0 | S68: 0 | T68: 0 | U68: 0.0132 | V68: 0 | W68: 0.023 | X68: 0 | Y68: =IFERROR(VLOOKUP(F:F,#REF!,2,0),"需要手动检查") -> 需要手动检查 | Z68: =IF(R68>0,"是","否") -> 否 | AA68: 3店-Faiable Comfywear | AB68: 商务 | AC68: =YEAR(E68)&"/"&MONTH(E68)&"/"&DAY(E68) -> 2024/12/23 | AD68: =VLOOKUP(Y68,#REF!,2,FALSE) -> #REF!
A69: mandolincarbo | B69: 6821501972416431109 | C69: Always posting up!! #tiktokshop #tiktokpartner #tiktok #jacket #hoodyseason | D69: 7451718469504175406 | E69: 45649.551 | F69: Hatant acid wash hoodie pullover oversized heavyweight cotton blend fleeced inside fabric comfy and baggy hoodies suitable for men and women faded craf vintage style hoodie | G69: 519 | H69: 10 | I69: 0 | J69: 1 | K69: 0 | L69: 0 | M69: 532 | N69: 35 | O69: 0 | P69: 0 | Q69: 0 | R69: 0 | S69: 0 | T69: 0 | U69: 0.0674 | V69: 0 | W69: 0.0771 | X69: 0 | Y69: =IFERROR(VLOOKUP(F:F,#REF!,2,0),"需要手动检查") -> 需要手动检查 | Z69: =IF(R69>0,"是","否") -> 否 | AA69: 3店-Faiable Comfywear | AB69: 商务 | AC69: =YEAR(E69)&"/"&MONTH(E69)&"/"&DAY(E69) -> 2024/12/23 | AD69: =VLOOKUP(Y69,#REF!,2,FALSE) -> #REF!
A70: chloe.dawn0 | B70: 17813527 | D70: 7451715198978755886 | E70: 45649.542 | F70: Hatant Stylish Street Fashion Pullover for Women with Soft Batwing Sleeves and Big Round Neck - Breathable and Comfortable Casual Sweatshirt for All-Day Wear | G70: 601 | H70: 43 | I70: 5 | J70: 0 | K70: 0 | L70: 0 | M70: 597 | N70: 25 | O70: 0 | P70: 0 | Q70: 0 | R70: 0 | S70: 0 | T70: 0 | U70: 0.0416 | V70: 0 | W70: 0.0466 | X70: 0 | Y70: =IFERROR(VLOOKUP(F:F,#REF!,2,0),"需要手动检查") -> 需要手动检查 | Z70: =IF(R70>0,"是","否") -> 否 | AA70: 3店-Faiable Comfywear | AB70: 商务 | AC70: =YEAR(E70)&"/"&MONTH(E70)&"/"&DAY(E70) -> 2024/12/23 | AD70: =VLOOKUP(Y70,#REF!,2,FALSE) -> #REF!
A71: christelholland | B71: 6737645537397670918 | C71: So cozzyyy #tiktokpartner #tiktokshopaffiliate #fyp | D71: 7451710506995305771 | E71: 45649.53 | F71: Hatant acid wash hoodie pullover oversized heavyweight cotton blend fleeced inside fabric comfy and baggy hoodies suitable for men and women faded craf vintage style hoodie | G71: 778 | H71: 28 | I71: 1 | J71: 0 | K71: 0 | L71: 0 | M71: 792 | N71: 42 | O71: 0 | P71: 0 | Q71: 0 | R71: 0 | S71: 0 | T71: 0 | U71: 0.054 | V71: 0 | W71: 0.0077 | X71: 0 | Y71: =IFERROR(VLOOKUP(F:F,#REF!,2,0),"需要手动检查") -> 需要手动检查 | Z71: =IF(R71>0,"是","否") -> 否 | AA71: 3店-Faiable Comfywear | AB71: 商务 | AC71: =YEAR(E71)&"/"&MONTH(E71)&"/"&DAY(E71) -> 2024/12/23 | AD71: =VLOOKUP(Y71,#REF!,2,FALSE) -> #REF!
A72: heatherk863 | B72: 7252373680461743147 | C72: Oversized hoodie #hoodie #acidwashhoodie #oversizedhoodie #winterwardroberefresh #faiablecomfywear | D72: 7451690048660999467 | E72: 45649.474 | F72: Hatant acid wash hoodie pullover oversized heavyweight cotton blend fleeced inside fabric comfy and baggy hoodies suitable for men and women faded craf vintage style hoodie | G72: 62 | H72: 14 | I72: 8 | J72: 1 | K72: 0 | L72: 0 | M72: 62 | N72: 1 | O72: 0 | P72: 0 | Q72: 0 | R72: 0 | S72: 0 | T72: 0 | U72: 0.0161 | V72: 0 | W72: 0.0806 | X72: 0 | Y72: =IFERROR(VLOOKUP(F:F,#REF!,2,0),"需要手动检查") -> 需要手动检查 | Z72: =IF(R72>0,"是","否") -> 否 | AA72: 3店-Faiable Comfywear | AB72: 商务 | AC72: =YEAR(E72)&"/"&MONTH(E72)&"/"&DAY(E72) -> 2024/12/23 | AD72: =VLOOKUP(Y72,#REF!,2,FALSE) -> #REF!
A73: momslife001 | B73: 6635674926881751045 | C73: Staying warm for the holidays!! ☃️🎄🎅🏻❤️ #believe #momsoftiktok #holidays #santa #christmas #tiktokshop #viraltiktok #fyp | D73: 7451666255808924958 | E73: 45649.411 | F73: Hatant acid wash hoodie pullover oversized heavyweight cotton blend fleeced inside fabric comfy and baggy hoodies suitable for men and women faded craf vintage style hoodie | G73: 545 | H73: 15 | I73: 0 | J73: 0 | K73: 0 | L73: 0 | M73: 519 | N73: 8 | O73: 0 | P73: 0 | Q73: 0 | R73: 0 | S73: 0 | T73: 0 | U73: 0.0147 | V73: 0 | W73: 0.1284 | X73: 0 | Y73: =IFERROR(VLOOKUP(F:F,#REF!,2,0),"需要手动检查") -> 需要手动检查 | Z73: =IF(R73>0,"是","否") -> 否 | AA73: 3店-Faiable Comfywear | AB73: 商务 | AC73: =YEAR(E73)&"/"&MONTH(E73)&"/"&DAY(E73) -> 2024/12/23 | AD73: =VLOOKUP(Y73,#REF!,2,FALSE) -> #REF!
A74: its_brenda_j | B74: 6823570932481721349 | C74: Snuggle up with this oversized hoodie, it’s thick and warm and soft and oversized and everything you want in outerwear this season! Not to mention this gorgeous color! #besthoodie #tiktokshophoodie #shophoodie #hoodie #hoodieszn #hoodieseason | D74: 7451644086450162990 | E74: 45649.351 | F74: Hatant acid wash hoodie pullover oversized heavyweight cotton blend fleeced inside fabric comfy and baggy hoodies suitable for men and women faded craf vintage style hoodie | G74: 448 | H74: 43 | I74: 11 | J74: 0 | K74: 0 | L74: 0 | M74: 493 | N74: 13 | O74: 0 | P74: 0 | Q74: 0 | R74: 0 | S74: 0 | T74: 0 | U74: 0.029 | V74: 0 | W74: 0.0379 | X74: 0 | Y74: =IFERROR(VLOOKUP(F:F,#REF!,2,0),"需要手动检查") -> 需要手动检查 | Z74: =IF(R74>0,"是","否") -> 否 | AA74: 3店-Faiable Comfywear | AB74: 商务 | AC74: =YEAR(E74)&"/"&MONTH(E74)&"/"&DAY(E74) -> 2024/12/23 | AD74: =VLOOKUP(Y74,#REF!,2,FALSE) -> #REF!
A75: onenac | B75: 7153393864009827370 | C75: 🎯 Looking for the PERFECT hoodie? Stop scrolling! I just got the Hatant Acid Wash Oversized Hoodie, and l love it so much is very cool 😎 10/10 ⭐️⭐️⭐️⭐️⭐️ 👏 Whether you’re lounging at home, running errands, or layering up for that perfect vintage vibe, this hoodie checks ALL the boxes. 🔥 What makes it amazing? Comfort that hugs you back: The fleeced inside feels like a warm cloud on your skin. Say goodbye to stiff, scratchy hoodies! Timeless vintage style: The acid wash gives off a faded, effortlessly cool vibe that matches everything from sweats to jeans. Unisex & versatile: Oversized fit? Check. Cozy AND stylish? Double check. This one’s a win for both men and women! 👚 Why you need this: If you’re tired of hoodies that don’t last, don’t fit right, or just don’t stand out this is your answer. The quality is INSANE, and the heavyweight cotton blend means it keeps its shape and softness, wash after wash. ⏳ Don’t wait this hoodie is going fast! Click the link in my video to grab yours and step up your hoodie game. #VintageVibes #ComfyStyle #TikTokMadeMeBuyIt | D75: 7451433526366440750 | E75: 45648.783 | F75: Hatant acid wash hoodie pullover oversized heavyweight cotton blend fleeced inside fabric comfy and baggy hoodies suitable for men and women faded craf vintage style hoodie | G75: 278 | H75: 6 | I75: 1 | J75: 2 | K75: 0 | L75: 0 | M75: 295 | N75: 3 | O75: 0 | P75: 0 | Q75: 0 | R75: 0 | S75: 0 | T75: 0 | U75: 0.0108 | V75: 0 | W75: 0.0036 | X75: 0 | Y75: =IFERROR(VLOOKUP(F:F,#REF!,2,0),"需要手动检查") -> 需要手动检查 | Z75: =IF(R75>0,"是","否") -> 否 | AA75: 3店-Faiable Comfywear | AB75: 商务 | AC75: =YEAR(E75)&"/"&MONTH(E75)&"/"&DAY(E75) -> 2024/12/22 | AD75: =VLOOKUP(Y75,#REF!,2,FALSE) -> #REF!
A76: syd.so.swag | B76: 6862518213159437318 | C76: I spilt oil on my new hoodie so posting this draft to remember her 🥲❤️ | D76: 7451433345218546986 | E76: 45648.783 | F76: Hatant acid wash hoodie pullover oversized heavyweight cotton blend fleeced inside fabric comfy and baggy hoodies suitable for men and women faded craf vintage style hoodie | G76: 564 | H76: 62 | I76: 4 | J76: 0 | K76: 0 | L76: 0 | M76: 561 | N76: 5 | O76: 0 | P76: 0 | Q76: 0 | R76: 0 | S76: 0 | T76: 0 | U76: 0.0089 | V76: 0 | W76: 0.0816 | X76: 0 | Y76: =IFERROR(VLOOKUP(F:F,#REF!,2,0),"需要手动检查") -> 需要手动检查 | Z76: =IF(R76>0,"是","否") -> 否 | AA76: 3店-Faiable Comfywear | AB76: 商务 | AC76: =YEAR(E76)&"/"&MONTH(E76)&"/"&DAY(E76) -> 2024/12/22 | AD76: =VLOOKUP(Y76,#REF!,2,FALSE) -> #REF!
A77: sansaluvs03greedo | B77: 6767530423201383429 | D77: 7451423624302562590 | E77: 45648.757 | F77: Hatant acid wash hoodie pullover oversized heavyweight cotton blend fleeced inside fabric comfy and baggy hoodies suitable for men and women faded craf vintage style hoodie | G77: 1434 | H77: 209 | I77: 3 | J77: 0 | K77: 0 | L77: 0 | M77: 1515 | N77: 17 | O77: 0 | P77: 0 | Q77: 0 | R77: 0 | S77: 0 | T77: 0 | U77: 0.0119 | V77: 0 | W77: 0.037 | X77: 0 | Y77: =IFERROR(VLOOKUP(F:F,#REF!,2,0),"需要手动检查") -> 需要手动检查 | Z77: =IF(R77>0,"是","否") -> 否 | AA77: 3店-Faiable Comfywear | AB77: 商务 | AC77: =YEAR(E77)&"/"&MONTH(E77)&"/"&DAY(E77) -> 2024/12/22 | AD77: =VLOOKUP(Y77,#REF!,2,FALSE) -> #REF!
A78: marteen2003 | B78: 6805300488839808006 | C78: #crewneck #sweatshirt #offtheshoulder | D78: 7451422110532046111 | E78: 45648.753 | F78: Hatant Stylish Street Fashion Pullover for Women with Soft Batwing Sleeves and Big Round Neck - Breathable and Comfortable Casual Sweatshirt for All-Day Wear | G78: 748 | H78: 33 | I78: 0 | J78: 0 | K78: 0 | L78: 0 | M78: 762 | N78: 66 | O78: 0 | P78: 0 | Q78: 0 | R78: 0 | S78: 0 | T78: 0 | U78: 0.0882 | V78: 0 | W78: 0.0267 | X78: 0 | Y78: =IFERROR(VLOOKUP(F:F,#REF!,2,0),"需要手动检查") -> 需要手动检查 | Z78: =IF(R78>0,"是","否") -> 否 | AA78: 3店-Faiable Comfywear | AB78: 商务 | AC78: =YEAR(E78)&"/"&MONTH(E78)&"/"&DAY(E78) -> 2024/12/22 | AD78: =VLOOKUP(Y78,#REF!,2,FALSE) -> #REF!
A79: yeehawyeett | B79: 6626850578973458438 | C79: I am actually so obsessed with this hoodie and have worn it so much since getting it!! 🩷 #tiktokshop #tiktokshophaul #cozyhoodie #sweatshirt #hoodie #pinkhoodie #pinksweatshirt #haul #unboxing #carhaul | D79: 7451389608228670766 | E79: 45648.665 | F79: Hatant acid wash hoodie pullover oversized heavyweight cotton blend fleeced inside fabric comfy and baggy hoodies suitable for men and women faded craf vintage style hoodie | G79: 471 | H79: 23 | I79: 1 | J79: 0 | K79: 1 | L79: 0 | M79: 487 | N79: 39 | O79: 0 | P79: 0 | Q79: 0 | R79: 0 | S79: 0 | T79: 0 | U79: 0.0828 | V79: 0 | W79: 0.0255 | X79: 0 | Y79: =IFERROR(VLOOKUP(F:F,#REF!,2,0),"需要手动检查") -> 需要手动检查 | Z79: =IF(R79>0,"是","否") -> 否 | AA79: 3店-Faiable Comfywear | AB79: 商务 | AC79: =YEAR(E79)&"/"&MONTH(E79)&"/"&DAY(E79) -> 2024/12/22 | AD79: =VLOOKUP(Y79,#REF!,2,FALSE) -> #REF!
A80: kerryc1208 | B80: 7355684352792052782 | C80: when I tell you I have been living in this!!! #tiktokshop #oversizedhoodie #bestoversizedhoodie #comfy #creatorsearchinsights #hoodie | D80: 7451384712192331050 | E80: 45648.652 | F80: Hatant acid wash hoodie pullover oversized heavyweight cotton blend fleeced inside fabric comfy and baggy hoodies suitable for men and women faded craf vintage style hoodie | G80: 280 | H80: 10 | I80: 1 | J80: 0 | K80: 0 | L80: 0 | M80: 289 | N80: 22 | O80: 0 | P80: 0 | Q80: 0 | R80: 0 | S80: 0 | T80: 0 | U80: 0.0786 | V80: 0 | W80: 0.0214 | X80: 0 | Y80: =IFERROR(VLOOKUP(F:F,#REF!,2,0),"需要手动检查") -> 需要手动检查 | Z80: =IF(R80>0,"是","否") -> 否 | AA80: 3店-Faiable Comfywear | AB80: 商务 | AC80: =YEAR(E80)&"/"&MONTH(E80)&"/"&DAY(E80) -> 2024/12/22 | AD80: =VLOOKUP(Y80,#REF!,2,FALSE) -> #REF!
A81: arelybabyy | B81: 2996823 | C81: Such a comfy & cute look 🎀 #oversizedhoodie #hoodie #pink #hoodies | D81: 7451368603041189166 | E81: 45648.608 | F81: Hatant acid wash hoodie pullover oversized heavyweight cotton blend fleeced inside fabric comfy and baggy hoodies suitable for men and women faded craf vintage style hoodie | G81: 395 | H81: 21 | I81: 2 | J81: 1 | K81: 0 | L81: 0 | M81: 411 | N81: 34 | O81: 0 | P81: 0 | Q81: 0 | R81: 0 | S81: 0 | T81: 0 | U81: 0.0861 | V81: 0 | W81: 0.0101 | X81: 0 | Y81: =IFERROR(VLOOKUP(F:F,#REF!,2,0),"需要手动检查") -> 需要手动检查 | Z81: =IF(R81>0,"是","否") -> 否 | AA81: 3店-Faiable Comfywear | AB81: 商务 | AC81: =YEAR(E81)&"/"&MONTH(E81)&"/"&DAY(E81) -> 2024/12/22 | AD81: =VLOOKUP(Y81,#REF!,2,FALSE) -> #REF!
A82: avedaviis | B82: 6616682790505906182 | C82: one of my fave sweatshirts 🖤 #offtheshouldersweatshirt #hoodiecollection #winterwardrobe | D82: 7451358546903584031 | E82: 45648.581 | F82: Hatant Stylish Street Fashion Pullover for Women with Soft Batwing Sleeves and Big Round Neck - Breathable and Comfortable Casual Sweatshirt for All-Day Wear | G82: 725 | H82: 23 | I82: 4 | J82: 1 | K82: 0 | L82: 0 | M82: 737 | N82: 17 | O82: 0 | P82: 0 | Q82: 0 | R82: 0 | S82: 0 | T82: 0 | U82: 0.0234 | V82: 0 | W82: 0.0262 | X82: 0 | Y82: =IFERROR(VLOOKUP(F:F,#REF!,2,0),"需要手动检查") -> 需要手动检查 | Z82: =IF(R82>0,"是","否") -> 否 | AA82: 3店-Faiable Comfywear | AB82: 商务 | AC82: =YEAR(E82)&"/"&MONTH(E82)&"/"&DAY(E82) -> 2024/12/22 | AD82: =VLOOKUP(Y82,#REF!,2,FALSE) -> #REF!
A83: rubia_670 | B83: 7047613787139163142 | C83: #fyp #rubia20 #hoodie #faiablehoodie #faiablefashion | D83: 7451351713929334062 | E83: 45648.563 | F83: Hatant acid wash hoodie pullover oversized heavyweight cotton blend fleeced inside fabric comfy and baggy hoodies suitable for men and women faded craf vintage style hoodie | G83: 3151 | H83: 159 | I83: 1 | J83: 0 | K83: 0 | L83: 0 | M83: 3309 | N83: 492 | O83: 0 | P83: 0 | Q83: 0 | R83: 0 | S83: 0 | T83: 0 | U83: 0.1561 | V83: 0 | W83: 0.007 | X83: 0 | Y83: =IFERROR(VLOOKUP(F:F,#REF!,2,0),"需要手动检查") -> 需要手动检查 | Z83: =IF(R83>0,"是","否") -> 否 | AA83: 3店-Faiable Comfywear | AB83: 商务 | AC83: =YEAR(E83)&"/"&MONTH(E83)&"/"&DAY(E83) -> 2024/12/22 | AD83: =VLOOKUP(Y83,#REF!,2,FALSE) -> #REF!
A84: msjessicapippin | B84: 6759694068467549189 | C84: An oversized sweater just makes me feel 10x better in oversized crowds. Ifykyk 🖤 | D84: 7451340242529078574 | E84: 45648.532 | F84: Hatant Stylish Street Fashion Pullover for Women with Soft Batwing Sleeves and Big Round Neck - Breathable and Comfortable Casual Sweatshirt for All-Day Wear | G84: 400 | H84: 38 | I84: 2 | J84: 0 | K84: 0 | L84: 0 | M84: 3 | N84: 0 | O84: 0 | P84: 0 | Q84: 0 | R84: 0 | S84: 0 | T84: 0 | U84: 0 | V84: 0 | W84: 0.055 | X84: 0 | Y84: =IFERROR(VLOOKUP(F:F,#REF!,2,0),"需要手动检查") -> 需要手动检查 | Z84: =IF(R84>0,"是","否") -> 否 | AA84: 3店-Faiable Comfywear | AB84: 商务 | AC84: =YEAR(E84)&"/"&MONTH(E84)&"/"&DAY(E84) -> 2024/12/22 | AD84: =VLOOKUP(Y84,#REF!,2,FALSE) -> #REF!
A85: jennmalentacchi2 | B85: 7319968933406688302 | C85: I know we all want the comfort of wearing our man sweatpants, but we don’t wanna deal with the stains so get your own. I promise they’re just as comfortable. @Faiable Fashion #Sweatpants #Loungewear #Unisex #UnisexSweatpants #Sweatsuit #GiftsForHer #GiftsForHim | D85: 7451336445102411039 | E85: 45648.522 | F85: Hatant heavyweight fleeced comfy and soft baggy sweatpants cotton 345gsm fabric S-2XL true size bottoms Elastic waistband drawstring | G85: 234 | H85: 4 | I85: 0 | J85: 0 | K85: 0 | L85: 0 | M85: 242 | N85: 1 | O85: 0 | P85: 0 | Q85: 0 | R85: 0 | S85: 0 | T85: 0 | U85: 0.0043 | V85: 0 | W85: 0 | X85: 0 | Y85: =IFERROR(VLOOKUP(F:F,#REF!,2,0),"需要手动检查") -> 需要手动检查 | Z85: =IF(R85>0,"是","否") -> 否 | AA85: 3店-Faiable Comfywear | AB85: 商务 | AC85: =YEAR(E85)&"/"&MONTH(E85)&"/"&DAY(E85) -> 2024/12/22 | AD85: =VLOOKUP(Y85,#REF!,2,FALSE) -> #REF!
A86: anneallenfloyd | B86: 6943755088012674054 | C86: #tiktokshop #oversizedshirt #sweatshirt #00 | D86: 7451324524127128863 | E86: 45648.49 | F86: Hatant Stylish Street Fashion Pullover for Women with Soft Batwing Sleeves and Big Round Neck - Breathable and Comfortable Casual Sweatshirt for All-Day Wear | G86: 4207 | H86: 933 | I86: 8 | J86: 0 | K86: 3 | L86: 0 | M86: 1450 | N86: 49 | O86: 0 | P86: 0 | Q86: 0 | R86: 0 | S86: 0 | T86: 0 | U86: 0.0116 | V86: 0 | W86: 0.0178 | X86: 0 | Y86: =IFERROR(VLOOKUP(F:F,#REF!,2,0),"需要手动检查") -> 需要手动检查 | Z86: =IF(R86>0,"是","否") -> 否 | AA86: 3店-Faiable Comfywear | AB86: 商务 | AC86: =YEAR(E86)&"/"&MONTH(E86)&"/"&DAY(E86) -> 2024/12/22 | AD86: =VLOOKUP(Y86,#REF!,2,FALSE) -> #REF!
A87: torijflow | B87: 6715264465669899270 | C87: Softest thing in the WORLD #faiablehoodie #lookforless #sweaterweather #sweatshirt #comfy #comfyclothes | D87: 7451318887611698463 | E87: 45648.474 | F87: Hatant Stylish Street Fashion Pullover for Women with Soft Batwing Sleeves and Big Round Neck - Breathable and Comfortable Casual Sweatshirt for All-Day Wear | G87: 1352 | H87: 23 | I87: 2 | J87: 1 | K87: 1 | L87: 0 | M87: 1426 | N87: 32 | O87: 0 | P87: 0 | Q87: 0 | R87: 0 | S87: 0 | T87: 0 | U87: 0.0237 | V87: 0 | W87: 0.0325 | X87: 0 | Y87: =IFERROR(VLOOKUP(F:F,#REF!,2,0),"需要手动检查") -> 需要手动检查 | Z87: =IF(R87>0,"是","否") -> 否 | AA87: 3店-Faiable Comfywear | AB87: 商务 | AC87: =YEAR(E87)&"/"&MONTH(E87)&"/"&DAY(E87) -> 2024/12/22 | AD87: =VLOOKUP(Y87,#REF!,2,FALSE) -> #REF!
A88: katiesantos_sahm65 | B88: 6786888663429301253 | C88: Comfy and oversized the perfect balance ✨ #oversized #fyp #momsoftiktok #comfy | D88: 7451275678470671647 | E88: 45648.358 | F88: FAIABLE Cozy, Comfortable, and Fashionable Unisex Street Fashion with Distressed Hoody Style - Long Sleeve Soft Fabric in Solid Color, Fade Craft and Elastic Fit - Perfect for a Retro Look | G88: 654 | H88: 7 | I88: 0 | J88: 0 | K88: 0 | L88: 0 | M88: 705 | N88: 1 | O88: 0 | P88: 0 | Q88: 0 | R88: 0 | S88: 0 | T88: 0 | U88: 0.0015 | V88: 0 | W88: 0.0107 | X88: 0 | Y88: =IFERROR(VLOOKUP(F:F,#REF!,2,0),"需要手动检查") -> 需要手动检查 | Z88: =IF(R88>0,"是","否") -> 否 | AA88: 3店-Faiable Comfywear | AB88: 商务 | AC88: =YEAR(E88)&"/"&MONTH(E88)&"/"&DAY(E88) -> 2024/12/22 | AD88: =VLOOKUP(Y88,#REF!,2,FALSE) -> #REF!
A89: ohsococorix | B89: 6774520989885137925 | C89: The perfect oversized, soft, cozy hoodie! #oversizedhoodie | D89: 7451261321644985646 | E89: 45648.319 | F89: Hatant acid wash hoodie pullover oversized heavyweight cotton blend fleeced inside fabric comfy and baggy hoodies suitable for men and women faded craf vintage style hoodie | G89: 407 | H89: 5 | I89: 0 | J89: 0 | K89: 0 | L89: 0 | M89: 413 | N89: 9 | O89: 0 | P89: 0 | Q89: 0 | R89: 0 | S89: 0 | T89: 0 | U89: 0.0221 | V89: 0 | W89: 0.0049 | X89: 0 | Y89: =IFERROR(VLOOKUP(F:F,#REF!,2,0),"需要手动检查") -> 需要手动检查 | Z89: =IF(R89>0,"是","否") -> 否 | AA89: 3店-Faiable Comfywear | AB89: 商务 | AC89: =YEAR(E89)&"/"&MONTH(E89)&"/"&DAY(E89) -> 2024/12/22 | AD89: =VLOOKUP(Y89,#REF!,2,FALSE) -> #REF!
... A98: maybemartyna | B98: 6895166061155845126 | C98: new item try-on!! faiable just never disappoints, so soft and flattering | D98: 7450971668740066591 | E98: 45647.539 | F98: Hatant acid wash hoodie pullover oversized heavyweight cotton blend fleeced inside fabric comfy and baggy hoodies suitable for men and women faded craf vintage style hoodie | G98: 42 | H98: 2 | I98: 0 | J98: 0 | K98: 0 | L98: 0 | M98: 29 | N98: 0 | O98: 0 | P98: 0 | Q98: 0 | R98: 0 | S98: 0 | T98: 0 | U98: 0 | V98: 0 | W98: 0.0238 | X98: 0 | Y98: =IFERROR(VLOOKUP(F:F,#REF!,2,0),"需要手动检查") -> 需要手动检查 | Z98: =IF(R98>0,"是","否") -> 否 | AA98: 3店-Faiable Comfywear | AB98: 商务 | AC98: =YEAR(E98)&"/"&MONTH(E98)&"/"&DAY(E98) -> 2024/12/21 | AD98: =VLOOKUP(Y98,#REF!,2,FALSE) -> #REF!
A99: _taniagrover | B99: 6720781669114201093 | D99: 7450942766122569002 | E99: 45647.461 | F99: Hatant acid wash hoodie pullover oversized heavyweight cotton blend fleeced inside fabric comfy and baggy hoodies suitable for men and women faded craf vintage style hoodie | G99: 497 | H99: 39 | I99: 2 | J99: 0 | K99: 1 | L99: 0 | M99: 444 | N99: 8 | O99: 0 | P99: 0 | Q99: 0 | R99: 0 | S99: 0 | T99: 0 | U99: 0.0161 | V99: 0 | W99: 0.0946 | X99: 0 | Y99: =IFERROR(VLOOKUP(F:F,#REF!,2,0),"需要手动检查") -> 需要手动检查 | Z99: =IF(R99>0,"是","否") -> 否 | AA99: 3店-Faiable Comfywear | AB99: 商务 | AC99: =YEAR(E99)&"/"&MONTH(E99)&"/"&DAY(E99) -> 2024/12/21 | AD99: =VLOOKUP(Y99,#REF!,2,FALSE) -> #REF!
A100: simplymonicalife | B100: 7369364602067272746 | C100: Cutest oversized hoodie💗 so comfy and cozy😭🥰 link above! #hoodie #hoodies #oversizedhoodie #oversized | D100: 7450927069183085854 | E100: 45647.419 | F100: Hatant acid wash hoodie pullover oversized heavyweight cotton blend fleeced inside fabric comfy and baggy hoodies suitable for men and women faded craf vintage style hoodie | G100: 470 | H100: 26 | I100: 0 | J100: 1 | K100: 2 | L100: 0 | M100: 486 | N100: 14 | O100: 0 | P100: 0 | Q100: 0 | R100: 0 | S100: 0 | T100: 0 | U100: 0.0298 | V100: 0 | W100: 0.0128 | X100: 0 | Y100: =IFERROR(VLOOKUP(F:F,#REF!,2,0),"需要手动检查") -> 需要手动检查 | Z100: =IF(R100>0,"是","否") -> 否 | AA100: 3店-Faiable Comfywear | AB100: 商务 | AC100: =YEAR(E100)&"/"&MONTH(E100)&"/"&DAY(E100) -> 2024/12/21 | AD100: =VLOOKUP(Y100,#REF!,2,FALSE) -> #REF!
A101: ashxxmx | B101: 6586415071030951942 | C101: literally the only hoodie i reach for now #hoodie #tiktokshop #holiday #christmas #christmasgift #winter | D101: 7450913868747951402 | E101: 45647.383 | F101: Hatant acid wash hoodie pullover oversized heavyweight cotton blend fleeced inside fabric comfy and baggy hoodies suitable for men and women faded craf vintage style hoodie | G101: 541 | H101: 32 | I101: 3 | J101: 1 | K101: 0 | L101: 0 | M101: 570 | N101: 37 | O101: 0 | P101: 0 | Q101: 0 | R101: 0 | S101: 0 | T101: 0 | U101: 0.0684 | V101: 0 | W101: 0.0407 | X101: 0 | Y101: =IFERROR(VLOOKUP(F:F,#REF!,2,0),"需要手动检查") -> 需要手动检查 | Z101: =IF(R101>0,"是","否") -> 否 | AA101: 3店-Faiable Comfywear | AB101: 商务 | AC101: =YEAR(E101)&"/"&MONTH(E101)&"/"&DAY(E101) -> 2024/12/21 | AD101: =VLOOKUP(Y101,#REF!,2,FALSE) -> #REF!
A102: tessiahamilton_ | B102: 6834968086928458758 | D102: 7450896108181769518 | E102: 45647.335 | F102: Hatant acid wash hoodie pullover oversized heavyweight cotton blend fleeced inside fabric comfy and baggy hoodies suitable for men and women faded craf vintage style hoodie | G102: 1004 | H102: 65 | I102: 3 | J102: 0 | K102: 0 | L102: 0 | M102: 722 | N102: 6 | O102: 0 | P102: 0 | Q102: 0 | R102: 0 | S102: 0 | T102: 0 | U102: 0.006 | V102: 0 | W102: 0.0797 | X102: 0 | Y102: =IFERROR(VLOOKUP(F:F,#REF!,2,0),"需要手动检查") -> 需要手动检查 | Z102: =IF(R102>0,"是","否") -> 否 | AA102: 3店-Faiable Comfywear | AB102: 商务 | AC102: =YEAR(E102)&"/"&MONTH(E102)&"/"&DAY(E102) -> 2024/12/21 | AD102: =VLOOKUP(Y102,#REF!,2,FALSE) -> #REF!
A103: myyfavoritethingss | B103: 7353463817287042091 | C103: i love a good hoodie #hoodiethathoodies #hoodies #outfitinspo | D103: 7450751789931973931 | E103: 45646.946 | F103: Hatant acid wash hoodie pullover oversized heavyweight cotton blend fleeced inside fabric comfy and baggy hoodies suitable for men and women faded craf vintage style hoodie | G103: 400 | H103: 15 | I103: 5 | J103: 1 | K103: 0 | L103: 0 | M103: 400 | N103: 9 | O103: 0 | P103: 0 | Q103: 0 | R103: 0 | S103: 0 | T103: 0 | U103: 0.0225 | V103: 0 | W103: 0.04 | X103: 0 | Y103: =IFERROR(VLOOKUP(F:F,#REF!,2,0),"需要手动检查") -> 需要手动检查 | Z103: =IF(R103>0,"是","否") -> 否 | AA103: 3店-Faiable Comfywear | AB103: 商务 | AC103: =YEAR(E103)&"/"&MONTH(E103)&"/"&DAY(E103) -> 2024/12/20 | AD103: =VLOOKUP(Y103,#REF!,2,FALSE) -> #REF!
A104: namastaylivin | B104: 7067316750894859310 | C104: An oversized hoodie for the comfy-ness ocassion- catch me cozy all day long #hoodie #pullover #pulloverhoodie #oversized #giftguide #TTSDelight #TikTokShopHolidayHaul #TikTokShopYearEndSale | D104: 7450708910052363562 | E104: 45646.83 | F104: Hatant acid wash hoodie pullover oversized heavyweight cotton blend fleeced inside fabric comfy and baggy hoodies suitable for men and women faded craf vintage style hoodie | G104: 306 | H104: 11 | I104: 2 | J104: 1 | K104: 1 | L104: 0 | M104: 324 | N104: 30 | O104: 0 | P104: 0 | Q104: 0 | R104: 0 | S104: 0 | T104: 0 | U104: 0.098 | V104: 0 | W104: 0.0098 | X104: 0 | Y104: =IFERROR(VLOOKUP(F:F,#REF!,2,0),"需要手动检查") -> 需要手动检查 | Z104: =IF(R104>0,"是","否") -> 否 | AA104: 3店-Faiable Comfywear | AB104: 商务 | AC104: =YEAR(E104)&"/"&MONTH(E104)&"/"&DAY(E104) -> 2024/12/20 | AD104: =VLOOKUP(Y104,#REF!,2,FALSE) -> #REF!
A105: rsc530 | B105: 6954614798215005190 | C105: #giftforher #fashiontiktok #holidaygifts #gift #bestsellingproducts | D105: 7450699873764035870 | E105: 45646.806 | F105: Hatant Stylish Street Fashion Pullover for Women with Soft Batwing Sleeves and Big Round Neck - Breathable and Comfortable Casual Sweatshirt for All-Day Wear | G105: 331 | H105: 5 | I105: 1 | J105: 3 | K105: 1 | L105: 0 | M105: 341 | N105: 3 | O105: 0 | P105: 0 | Q105: 0 | R105: 0 | S105: 0 | T105: 0 | U105: 0.0091 | V105: 0 | W105: 0 | X105: 0 | Y105: =IFERROR(VLOOKUP(F:F,#REF!,2,0),"需要手动检查") -> 需要手动检查 | Z105: =IF(R105>0,"是","否") -> 否 | AA105: 3店-Faiable Comfywear | AB105: 商务 | AC105: =YEAR(E105)&"/"&MONTH(E105)&"/"&DAY(E105) -> 2024/12/20 | AD105: =VLOOKUP(Y105,#REF!,2,FALSE) -> #REF!
A106: morganharrell1 | B106: 85738887968370688 | C106: The best hoodie from TikTok Shop & it the perfect pink🎀🤩✨🫶🏻 #fyp #foryoupage #viraltiktok #hoodie #pink #freeshipping #fuzzy #thick #hoodieseason #hoodies #hoodieszn #obsessed #perfect #onsalenow️️️🔥🔥🔥🔥 #hurryup #comfortable #af #viralvideo #engage #iengagewithmysupporters #loveyouall | D106: 7450651627939351854 | E106: 45646.676 | F106: Hatant acid wash hoodie pullover oversized heavyweight cotton blend fleeced inside fabric comfy and baggy hoodies suitable for men and women faded craf vintage style hoodie | G106: 357 | H106: 39 | I106: 2 | J106: 0 | K106: 1 | L106: 0 | M106: 361 | N106: 4 | O106: 0 | P106: 0 | Q106: 0 | R106: 0 | S106: 0 | T106: 0 | U106: 0.0112 | V106: 0 | W106: 0.0224 | X106: 0 | Y106: =IFERROR(VLOOKUP(F:F,#REF!,2,0),"需要手动检查") -> 需要手动检查 | Z106: =IF(R106>0,"是","否") -> 否 | AA106: 3店-Faiable Comfywear | AB106: 商务 | AC106: =YEAR(E106)&"/"&MONTH(E106)&"/"&DAY(E106) -> 2024/12/20 | AD106: =VLOOKUP(Y106,#REF!,2,FALSE) -> #REF!
A107: jillian.duvall | B107: 6875400283892941829 | C107: fav hoodie and one of my fav songs 🩷 - #comfyclothes #comfyhoodie #foryoupage #pinkhair #g59 #sb #scrim #rubydacherry #furryboots #fuzzybootsoutfits | D107: 7450644987517193515 | E107: 45646.658 | F107: Hatant acid wash hoodie pullover oversized heavyweight cotton blend fleeced inside fabric comfy and baggy hoodies suitable for men and women faded craf vintage style hoodie | G107: 4942 | H107: 852 | I107: 5 | J107: 5 | K107: 103 | L107: 0 | M107: 5553 | N107: 711 | O107: 0 | P107: 0 | Q107: 0 | R107: 0 | S107: 0 | T107: 0 | U107: 0.1439 | V107: 0 | W107: 0.122 | X107: 0 | Y107: =IFERROR(VLOOKUP(F:F,#REF!,2,0),"需要手动检查") -> 需要手动检查 | Z107: =IF(R107>0,"是","否") -> 否 | AA107: 3店-Faiable Comfywear | AB107: 商务 | AC107: =YEAR(E107)&"/"&MONTH(E107)&"/"&DAY(E107) -> 2024/12/20 | AD107: =VLOOKUP(Y107,#REF!,2,FALSE) -> #REF!
A108: noemischults | B108: 7174787525012423726 | C108: Living my best cozy life 🖤✨#NewYearNewAura #ttshop #holidayhaul #ComfyAndChic #CozyOOTD #momlifeuniform | D108: 7450642637989645598 | E108: 45646.652 | F108: Hatant acid wash hoodie pullover oversized heavyweight cotton blend fleeced inside fabric comfy and baggy hoodies suitable for men and women faded craf vintage style hoodie | G108: 316 | H108: 3 | I108: 0 | J108: 0 | K108: 0 | L108: 0 | M108: 11 | N108: 1 | O108: 0 | P108: 0 | Q108: 0 | R108: 0 | S108: 0 | T108: 0 | U108: 0.0032 | V108: 0 | W108: 0.0411 | X108: 0 | Y108: =IFERROR(VLOOKUP(F:F,#REF!,2,0),"需要手动检查") -> 需要手动检查 | Z108: =IF(R108>0,"是","否") -> 否 | AA108: 3店-Faiable Comfywear | AB108: 商务 | AC108: =YEAR(E108)&"/"&MONTH(E108)&"/"&DAY(E108) -> 2024/12/20 | AD108: =VLOOKUP(Y108,#REF!,2,FALSE) -> #REF!
A109: sassmasterr | B109: 6727427814297502725 | C109: 💙🦋 | D109: 7450637256014056746 | E109: 45646.637 | F109: Hatant acid wash hoodie pullover oversized heavyweight cotton blend fleeced inside fabric comfy and baggy hoodies suitable for men and women faded craf vintage style hoodie | G109: 346 | H109: 38 | I109: 0 | J109: 1 | K109: 3 | L109: 0 | M109: 354 | N109: 5 | O109: 0 | P109: 0 | Q109: 0 | R109: 0 | S109: 0 | T109: 0 | U109: 0.0145 | V109: 0 | W109: 0.0665 | X109: 0 | Y109: =IFERROR(VLOOKUP(F:F,#REF!,2,0),"需要手动检查") -> 需要手动检查 | Z109: =IF(R109>0,"是","否") -> 否 | AA109: 3店-Faiable Comfywear | AB109: 商务 | AC109: =YEAR(E109)&"/"&MONTH(E109)&"/"&DAY(E109) -> 2024/12/20 | AD109: =VLOOKUP(Y109,#REF!,2,FALSE) -> #REF!
A110: crystalann3260 | B110: 6793063934327079941 | C110: This sweatshirt will need to be peeled off my body thank you 🤌🏼#fashiontiktok #winterfashion #sweatshirt #oversizedhoodie | D110: 7450622237679291691 | E110: 45646.597 | F110: Hatant Stylish Street Fashion Pullover for Women with Soft Batwing Sleeves and Big Round Neck - Breathable and Comfortable Casual Sweatshirt for All-Day Wear | G110: 389 | H110: 14 | I110: 0 | J110: 1 | K110: 1 | L110: 0 | M110: 392 | N110: 5 | O110: 0 | P110: 0 | Q110: 0 | R110: 0 | S110: 0 | T110: 0 | U110: 0.0129 | V110: 0 | W110: 0.036 | X110: 0 | Y110: =IFERROR(VLOOKUP(F:F,#REF!,2,0),"需要手动检查") -> 需要手动检查 | Z110: =IF(R110>0,"是","否") -> 否 | AA110: 3店-Faiable Comfywear | AB110: 商务 | AC110: =YEAR(E110)&"/"&MONTH(E110)&"/"&DAY(E110) -> 2024/12/20 | AD110: =VLOOKUP(Y110,#REF!,2,FALSE) -> #REF!
A111: prettymarieee5 | B111: 6732890388967195654 | D111: 7450614035696848174 | E111: 45646.575 | F111: Hatant acid wash hoodie pullover oversized heavyweight cotton blend fleeced inside fabric comfy and baggy hoodies suitable for men and women faded craf vintage style hoodie | G111: 36 | H111: 2 | I111: 0 | J111: 0 | K111: 0 | L111: 0 | M111: 47 | N111: 0 | O111: 0 | P111: 0 | Q111: 0 | R111: 0 | S111: 0 | T111: 0 | U111: 0 | V111: 0 | W111: 0 | X111: 0 | Y111: =IFERROR(VLOOKUP(F:F,#REF!,2,0),"需要手动检查") -> 需要手动检查 | Z111: =IF(R111>0,"是","否") -> 否 | AA111: 3店-Faiable Comfywear | AB111: 商务 | AC111: =YEAR(E111)&"/"&MONTH(E111)&"/"&DAY(E111) -> 2024/12/20 | AD111: =VLOOKUP(Y111,#REF!,2,FALSE) -> #REF!
A112: jkhanji | B112: 6891668485484299270 | C112: Favorite hoodie #hoodie #faiable #home #clothing #hoodies #comfy #thickhoodie #tholidayhaul #gifts #tiktokshopholidayhaul #christmas #christmasgift #menclothes #gift #womensclothing #oversizedhoodie | D112: 7450597976407362847 | E112: 45646.532 | F112: Hatant acid wash hoodie pullover oversized heavyweight cotton blend fleeced inside fabric comfy and baggy hoodies suitable for men and women faded craf vintage style hoodie | G112: 329 | H112: 4 | I112: 0 | J112: 0 | K112: 1 | L112: 0 | M112: 361 | N112: 21 | O112: 0 | P112: 0 | Q112: 0 | R112: 0 | S112: 0 | T112: 0 | U112: 0.0638 | V112: 0 | W112: 0 | X112: 0 | Y112: =IFERROR(VLOOKUP(F:F,#REF!,2,0),"需要手动检查") -> 需要手动检查 | Z112: =IF(R112>0,"是","否") -> 否 | AA112: 3店-Faiable Comfywear | AB112: 商务 | AC112: =YEAR(E112)&"/"&MONTH(E112)&"/"&DAY(E112) -> 2024/12/20 | AD112: =VLOOKUP(Y112,#REF!,2,FALSE) -> #REF!
A113: briaburton | B113: 2852722 | C113: fit from tiktok shop #fitcheck #tiktokshop #tiktokshopfinds #flyingbananajeans #oversizedhoodie | D113: 7450583478338325791 | E113: 45646.493 | F113: Hatant acid wash hoodie pullover oversized heavyweight cotton blend fleeced inside fabric comfy and baggy hoodies suitable for men and women faded craf vintage style hoodie | G113: 411 | H113: 62 | I113: 0 | J113: 0 | K113: 5 | L113: 0 | M113: 11 | N113: 2 | O113: 0 | P113: 0 | Q113: 0 | R113: 0 | S113: 0 | T113: 0 | U113: 0.0049 | V113: 0 | W113: 0.0341 | X113: 0 | Y113: =IFERROR(VLOOKUP(F:F,#REF!,2,0),"需要手动检查") -> 需要手动检查 | Z113: =IF(R113>0,"是","否") -> 否 | AA113: 3店-Faiable Comfywear | AB113: 商务 | AC113: =YEAR(E113)&"/"&MONTH(E113)&"/"&DAY(E113) -> 2024/12/20 | AD113: =VLOOKUP(Y113,#REF!,2,FALSE) -> #REF!
A114: lydiargibbs | B114: 6792944121154749446 | C114: obsessed w red hoodies lately🍒 such a trendy, vibrant color #hoodie #hoodieszn #tiktokshop | D114: 7450577789176040734 | E114: 45646.477 | F114: Hatant acid wash hoodie pullover oversized heavyweight cotton blend fleeced inside fabric comfy and baggy hoodies suitable for men and women faded craf vintage style hoodie | G114: 522 | H114: 48 | I114: 7 | J114: 2 | K114: 0 | L114: 0 | M114: 571 | N114: 9 | O114: 0 | P114: 0 | Q114: 0 | R114: 0 | S114: 0 | T114: 0 | U114: 0.0172 | V114: 0 | W114: 0.0345 | X114: 0 | Y114: =IFERROR(VLOOKUP(F:F,#REF!,2,0),"需要手动检查") -> 需要手动检查 | Z114: =IF(R114>0,"是","否") -> 否 | AA114: 3店-Faiable Comfywear | AB114: 商务 | AC114: =YEAR(E114)&"/"&MONTH(E114)&"/"&DAY(E114) -> 2024/12/20 | AD114: =VLOOKUP(Y114,#REF!,2,FALSE) -> #REF!
A115: babydoll2184 | B115: 7278781012866958378 | C115: Im in love with the color and quality. I need about 10 more of these please.❤️😊@Faiable Comfywear #faiablecomfywear #hoodie #pink #unisex | D115: 7450548918846246187 | E115: 45646.399 | F115: Hatant acid wash hoodie pullover oversized heavyweight cotton blend fleeced inside fabric comfy and baggy hoodies suitable for men and women faded craf vintage style hoodie | G115: 2364 | H115: 91 | I115: 4 | J115: 0 | K115: 3 | L115: 0 | M115: 2467 | N115: 37 | O115: 0 | P115: 0 | Q115: 0 | R115: 0 | S115: 0 | T115: 0 | U115: 0.0157 | V115: 0 | W115: 0.014 | X115: 0 | Y115: =IFERROR(VLOOKUP(F:F,#REF!,2,0),"需要手动检查") -> 需要手动检查 | Z115: =IF(R115>0,"是","否") -> 否 | AA115: 3店-Faiable Comfywear | AB115: 商务 | AC115: =YEAR(E115)&"/"&MONTH(E115)&"/"&DAY(E115) -> 2024/12/20 | AD115: =VLOOKUP(Y115,#REF!,2,FALSE) -> #REF!
A116: thekallumfam | B116: 6934353453536527365 | C116: #toddlersoftiktok #tiktokshop | D116: 7450531534915783967 | E116: 45646.353 | F116: Hatant acid wash hoodie pullover oversized heavyweight cotton blend fleeced inside fabric comfy and baggy hoodies suitable for men and women faded craf vintage style hoodie | G116: 1703 | H116: 88 | I116: 0 | J116: 1 | K116: 0 | L116: 0 | M116: 1775 | N116: 57 | O116: 0 | P116: 0 | Q116: 0 | R116: 0 | S116: 0 | T116: 0 | U116: 0.0335 | V116: 0 | W116: 0.3048 | X116: 0 | Y116: =IFERROR(VLOOKUP(F:F,#REF!,2,0),"需要手动检查") -> 需要手动检查 | Z116: =IF(R116>0,"是","否") -> 否 | AA116: 3店-Faiable Comfywear | AB116: 商务 | AC116: =YEAR(E116)&"/"&MONTH(E116)&"/"&DAY(E116) -> 2024/12/20 | AD116: =VLOOKUP(Y116,#REF!,2,FALSE) -> #REF!
A117: kerryc1208 | B117: 7355684352792052782 | C117: this oversized hoodie is my sahm outfit every day now. #oversizedhoodie #hoodie #sweatshirt #sahmoutfit #creatorsearchinsights | D117: 7450531441752198446 | E117: 45646.352 | F117: Hatant acid wash hoodie pullover oversized heavyweight cotton blend fleeced inside fabric comfy and baggy hoodies suitable for men and women faded craf vintage style hoodie | G117: 348 | H117: 26 | I117: 2 | J117: 1 | K117: 0 | L117: 0 | M117: 360 | N117: 20 | O117: 0 | P117: 0 | Q117: 0 | R117: 0 | S117: 0 | T117: 0 | U117: 0.0575 | V117: 0 | W117: 0.0287 | X117: 0 | Y117: =IFERROR(VLOOKUP(F:F,#REF!,2,0),"需要手动检查") -> 需要手动检查 | Z117: =IF(R117>0,"是","否") -> 否 | AA117: 3店-Faiable Comfywear | AB117: 商务 | AC117: =YEAR(E117)&"/"&MONTH(E117)&"/"&DAY(E117) -> 2024/12/20 | AD117: =VLOOKUP(Y117,#REF!,2,FALSE) -> #REF!
A118: kerryc1208 | B118: 7355684352792052782 | C118: this oversized hoodie is my sahm outfit every day now. #oversizedhoodie #hoodie #sweatshirt #sahmoutfit #creatorsearchinsights | D118: 7450530685942517038 | E118: 45646.35 | F118: Hatant acid wash hoodie pullover oversized heavyweight cotton blend fleeced inside fabric comfy and baggy hoodies suitable for men and women faded craf vintage style hoodie | G118: 6 | H118: 1 | I118: 0 | J118: 0 | K118: 0 | L118: 0 | M118: 1 | N118: 0 | O118: 0 | P118: 0 | Q118: 0 | R118: 0 | S118: 0 | T118: 0 | U118: 0 | V118: 0 | W118: 0 | X118: 0 | Y118: =IFERROR(VLOOKUP(F:F,#REF!,2,0),"需要手动检查") -> 需要手动检查 | Z118: =IF(R118>0,"是","否") -> 否 | AA118: 3店-Faiable Comfywear | AB118: 商务 | AC118: =YEAR(E118)&"/"&MONTH(E118)&"/"&DAY(E118) -> 2024/12/20 | AD118: =VLOOKUP(Y118,#REF!,2,FALSE) -> #REF!
A119: emislayyy | B119: 6895939578340803590 | C119: sweatshirt makes me feel like barbie 🎀🩷🩷🩷 | D119: 7450495501536922922 | E119: 45646.255 | F119: Hatant acid wash hoodie pullover oversized heavyweight cotton blend fleeced inside fabric comfy and baggy hoodies suitable for men and women faded craf vintage style hoodie | G119: 2558 | H119: 85 | I119: 1 | J119: 0 | K119: 1 | L119: 0 | M119: 2673 | N119: 60 | O119: 0 | P119: 0 | Q119: 0 | R119: 0 | S119: 0 | T119: 0 | U119: 0.0235 | V119: 0 | W119: 0.0403 | X119: 0 | Y119: =IFERROR(VLOOKUP(F:F,#REF!,2,0),"需要手动检查") -> 需要手动检查 | Z119: =IF(R119>0,"是","否") -> 否 | AA119: 3店-Faiable Comfywear | AB119: 商务 | AC119: =YEAR(E119)&"/"&MONTH(E119)&"/"&DAY(E119) -> 2024/12/20 | AD119: =VLOOKUP(Y119,#REF!,2,FALSE) -> #REF!
A120: faiablecomfywear | B120: 6901599748218962949 | D120: 7450400445220080926 | E120: 45647.01 | G120: 0 | H120: 0 | I120: 0 | J120: 0 | K120: 0 | L120: 0 | M120: 3 | N120: 0 | O120: 0 | P120: 0 | Q120: 0 | R120: 0 | S120: 0 | T120: 0 | U120: 0 | V120: 0 | W120: 0 | X120: 0 | Y120: =IFERROR(VLOOKUP(F:F,#REF!,2,0),"需要手动检查") -> 需要手动检查 | Z120: =IF(R120>0,"是","否") -> 否 | AA120: 3店-Faiable Comfywear | AB120: 剪辑 | AC120: =YEAR(E120)&"/"&MONTH(E120)&"/"&DAY(E120) -> 2024/12/21 | AD120: =VLOOKUP(Y120,#REF!,2,FALSE) -> #REF!
A121: faiablecomfywear | B121: 6901599748218962949 | D121: 7450400434876927262 | E121: 45648.01 | G121: 0 | H121: 0 | I121: 0 | J121: 0 | K121: 0 | L121: 0 | M121: 1 | N121: 0 | O121: 0 | P121: 0 | Q121: 0 | R121: 0 | S121: 0 | T121: 0 | U121: 0 | V121: 0 | W121: 0 | X121: 0 | Y121: =IFERROR(VLOOKUP(F:F,#REF!,2,0),"需要手动检查") -> 需要手动检查 | Z121: =IF(R121>0,"是","否") -> 否 | AA121: 3店-Faiable Comfywear | AB121: 剪辑 | AC121: =YEAR(E121)&"/"&MONTH(E121)&"/"&DAY(E121) -> 2024/12/22 | AD121: =VLOOKUP(Y121,#REF!,2,FALSE) -> #REF!
...
